{
	"info": {
		"_postman_id": "b538780e-2fa2-4e6e-98a2-d887f0260b18",
		"name": "SpacePlanning API",
		"schema": "https://schema.getpostman.com/json/collection/v2.1.0/collection.json"
	},
	"item": [
		{
			"name": "sobeys-sapevents-p-api-v1",
			"item": [
				{
					"name": "Sites",
					"request": {
						"method": "POST",
						"header": [
							{
								"key": "x-client-id",
								"value": "98e168ab576041a7b3b3cfee2e957acb",
								"type": "text"
							},
							{
								"key": "x-client-secret",
								"value": "6CbA485f7dC3479FB0C8a4401b5BA43a",
								"type": "text"
							}
						],
						"body": {
							"mode": "raw",
							"raw": "{\r\n  \"uuid\": \"480fcc9e-15ee-11ec-9621-0242ac1377ss\",\r\n  \"objectType\": \"site\",\r\n  \"regionName\": \"AMS\",\r\n  \"containerName\": \"sap-sites\",\r\n  \"sapData\": {\"SapData\":[{\"SITE\":\"0370\",\"SapBasicData\":{\"SITE_CATEGORY\":\"A\",\"SITE_PROFILE\":\"Z110\",\"BANNER_CODE\":\"005\",\"BANNER_NAME\":\"SOBEYS\",\"DISTRIBUTION_CHANNEL\":\"48\",\"RETAILER_SITE_ID\":\"ISF_11545\",\"RETAILER_REGION_ID\":\"ISF_NS01\",\"PRICING_REFERENCE_SITE\":\"0370\",\"PUBLIC_OPEN_DATE\":\"1972-05-30\",\"PUBLIC_CLOSE_DATE\":\"9999-12-30\",\"ACTIVE\":\"A\",\"CREATED_ON\":\"1998-01-16\"},\"SapDescription\":{\"SITE_NAME\":\"Sobeys Aberdeen Mall Store - 0\",\"ALTERNATE_SITE_NAME\":\"Sobeys Aberdeen Mall Store - 0\",\"SITE_PROFILE_DESCRIPTION\":\"Sobeys Store - Corporate\"},\"SapLocationInfo\":{\"LOCATION_ID\":\"11545\",\"LONGITUDE\":-6.2640156E+1,\"LATITUDE\":4.5577611E+1,\"STORE_TIME_ZONE\":\"AST\",\"LANGUAGE\":\"E\",\"COUNTRY\":\"CA\",\"PROVINCE\":\"NS\",\"CITY\":\"New Glasgow\",\"POSTAL_CODE\":\"B2H 3S2\",\"STREET_ADDRESS\":\"Aberdeen Mall 610 East River R\",\"TAX_JURISDICTION\":\"CANS\"},\"SapContactInfo\":{\"STORE_CONTACT\":\",,574695701412207\",\"EMAIL\":\"00370@sobeys.com\",\"TELEPHONE\":\"902-752-1066\"},\"SapStoreHours\":{\"STORE_OPEN_HOURS\":\"003\",\"MONDAY_OPEN_TIME\":\"00:01:00\",\"MONDAY_CLOSE_TIME\":\"23:59:00\",\"TUESDAY_OPEN_TIME\":\"00:01:00\",\"TUESDAY_CLOSE_TIME\":\"23:59:00\",\"WEDNESDAY_OPEN_TIME\":\"00:01:00\",\"WEDNESDAY_CLOSE_TIME\":\"23:59:00\",\"THURSDAY_OPEN_TIME\":\"00:01:00\",\"THURSDAY_CLOSE_TIME\":\"23:59:00\",\"FRIDAY_OPEN_TIME\":\"00:01:00\",\"FRIDAY_CLOSE_TIME\":\"23:59:00\",\"SATURDAY_OPEN_TIME\":\"00:01:00\",\"SATURDAY_CLOSE_TIME\":\"23:59:00\",\"SUNDAY_OPEN_TIME\":\"00:01:00\",\"SUNDAY_CLOSE_TIME\":\"23:59:00\"},\"SapSales\":{\"SALES_ORG\":\"3000\",\"SALES_OFFICE\":\"S2A\",\"SALES_AREA\":22828,\"SALES_AREA_UNIT\":\"FT2\",\"POS_INBOUND_PROFILE\":\"ZZNS\",\"POS_OUTBOUND_PROFILE\":\"ZALO\",\"POS_CURRENCY\":\"CAD\"},\"SapPurchasing\":{\"PURCH_ORG\":\"3000\",\"TAX_INDICATOR_PURCHASING\":\"1\"},\"SapAssortment\":{\"ASSORTMENT_LIST_OUTBOUND\":\"ZNIP\",\"STORE_LISTING_PROCEDURE\":\"Z1\",\"BASIC_RULE_LISTING\":\"1\"},\"SapMbs\":{\"MBS_REGION_NUMBER\":\"004\",\"MBS_REGION_DESCRIPTION\":\"SOBEYS ATLANTIC\"},\"SapDataOrigin\":{\"ECC_SYSTEM_IDENTITFIER\":\"AMS\",\"LOGICAL_SYSTEM\":\"DEV044\"}},{\"SITE\":\"3809\",\"SapBasicData\":{\"PUBLIC_OPEN_DATE\":\"0000-00-00\",\"PUBLIC_CLOSE_DATE\":\"0000-00-00\",\"CREATED_ON\":\"0000-00-00\"},\"SapDescription\":{\"SITE_NAME\":\"Voila by Sobeys CFC - Vaughan\"},\"SapLocationInfo\":{\"LONGITUDE\":0E+0,\"LATITUDE\":0E+0},\"SapContactInfo\":{\"STORE_CONTACT\":\"Deborah,,Harnett\"},\"SapStoreHours\":{\"MONDAY_OPEN_TIME\":\"00:00:00\",\"MONDAY_CLOSE_TIME\":\"00:00:00\",\"TUESDAY_OPEN_TIME\":\"00:00:00\",\"TUESDAY_CLOSE_TIME\":\"00:00:00\",\"WEDNESDAY_OPEN_TIME\":\"00:00:00\",\"WEDNESDAY_CLOSE_TIME\":\"00:00:00\",\"THURSDAY_OPEN_TIME\":\"00:00:00\",\"THURSDAY_CLOSE_TIME\":\"00:00:00\",\"FRIDAY_OPEN_TIME\":\"00:00:00\",\"FRIDAY_CLOSE_TIME\":\"00:00:00\",\"SATURDAY_OPEN_TIME\":\"00:00:00\",\"SATURDAY_CLOSE_TIME\":\"00:00:00\",\"SUNDAY_OPEN_TIME\":\"00:00:00\",\"SUNDAY_CLOSE_TIME\":\"00:00:00\"},\"SapSales\":{\"SALES_AREA\":0},\"SapPurchasing\":{},\"SapAssortment\":{},\"SapMbs\":{},\"SapDataOrigin\":{\"ECC_SYSTEM_IDENTITFIER\":\"AMS\",\"LOGICAL_SYSTEM\":\"DEV044\"}},{\"SITE\":\"3809\",\"SapBasicData\":{\"SITE_CATEGORY\":\"A\",\"SITE_PROFILE\":\"Z110\",\"DISTRIBUTION_CHANNEL\":\"58\",\"RETAILER_REGION_ID\":\"3809\",\"PRICING_REFERENCE_SITE\":\"3809\",\"PUBLIC_OPEN_DATE\":\"2019-03-15\",\"PUBLIC_CLOSE_DATE\":\"9999-12-31\",\"CREATED_ON\":\"2019-03-15\"},\"SapDescription\":{\"SITE_NAME\":\"Voila by Sobeys CFC - Vaughan\",\"ALTERNATE_SITE_NAME\":\"2431786703809\"},\"SapLocationInfo\":{\"LONGITUDE\":0E+0,\"LATITUDE\":0E+0,\"STORE_TIME_ZONE\":\"EST\",\"LANGUAGE\":\"E\",\"COUNTRY\":\"CA\",\"PROVINCE\":\"ON\",\"CITY\":\"Vaughan\",\"POSTAL_CODE\":\"L4L 1A5\",\"STREET_ADDRESS\":\"100 Gibraltar Road\",\"TAX_JURISDICTION\":\"CAON\"},\"SapContactInfo\":{},\"SapStoreHours\":{\"MONDAY_OPEN_TIME\":\"00:00:00\",\"MONDAY_CLOSE_TIME\":\"00:00:00\",\"TUESDAY_OPEN_TIME\":\"00:00:00\",\"TUESDAY_CLOSE_TIME\":\"00:00:00\",\"WEDNESDAY_OPEN_TIME\":\"00:00:00\",\"WEDNESDAY_CLOSE_TIME\":\"00:00:00\",\"THURSDAY_OPEN_TIME\":\"00:00:00\",\"THURSDAY_CLOSE_TIME\":\"00:00:00\",\"FRIDAY_OPEN_TIME\":\"00:00:00\",\"FRIDAY_CLOSE_TIME\":\"00:00:00\",\"SATURDAY_OPEN_TIME\":\"00:00:00\",\"SATURDAY_CLOSE_TIME\":\"00:00:00\",\"SUNDAY_OPEN_TIME\":\"00:00:00\",\"SUNDAY_CLOSE_TIME\":\"00:00:00\"},\"SapSales\":{\"SALES_ORG\":\"4000\",\"SALES_OFFICE\":\"407\",\"SALES_AREA\":0,\"POS_INBOUND_PROFILE\":\"ZCFC\",\"POS_OUTBOUND_PROFILE\":\"SAPD\",\"POS_CURRENCY\":\"CAD\"},\"SapPurchasing\":{\"PURCH_ORG\":\"4000\",\"TAX_INDICATOR_PURCHASING\":\"1\"},\"SapAssortment\":{\"ASSORTMENT_LIST_OUTBOUND\":\"ZCFC\",\"STORE_LISTING_PROCEDURE\":\"Z1\",\"BASIC_RULE_LISTING\":\"1\"},\"SapMbs\":{},\"SapDataOrigin\":{\"ECC_SYSTEM_IDENTITFIER\":\"OMS\",\"LOGICAL_SYSTEM\":\"DEV042\"}}]}\r\n}",
							"options": {
								"raw": {
									"language": "json"
								}
							}
						},
						"url": {
							"raw": "https://nonprod.apis.sobeys.com/dev/sobeys-sapevents-p-api/v1/uploadData",
							"protocol": "https",
							"host": [
								"nonprod",
								"apis",
								"sobeys",
								"com"
							],
							"path": [
								"dev",
								"sobeys-sapevents-p-api",
								"v1",
								"uploadData"
							]
						}
					},
					"response": []
				},
				{
					"name": "Products",
					"request": {
						"method": "POST",
						"header": [
							{
								"key": "x-client-id",
								"value": "98e168ab576041a7b3b3cfee2e957acb",
								"type": "text"
							},
							{
								"key": "x-client-secret",
								"value": "6CbA485f7dC3479FB0C8a4401b5BA43a",
								"type": "text"
							}
						],
						"body": {
							"mode": "raw",
							"raw": "{\r\n  \"uuid\": \"480fcc9e-15ee-11ec-9621-0242ac1377pp\",\r\n  \"objectType\": \"product\",\r\n  \"regionName\": \"AMS\",\r\n  \"containerName\": \"sap-product\",\r\n  \"sapData\": {\"SapData\":[{\"ARTICLE_NUMBER\":\"000000000000044218\",\"SALES_ORGANIZATION\":\"3000\",\"SapArticlebasicdata\":{\"ARTICLE_TYPE\":\"ZRIP\",\"MERCHANDISE_CATEGORY\":\"40-15-03\",\"BASE_UNIT_OF_MEASURE\":\"KG\",\"NET_WEIGHT\":1.000,\"CONTAINER_REQUIREMENTS\":null,\"PRODUCT_HIERARCHY\":null,\"PACKAGING_MATERIAL_TYPE\":null,\"EMPTIES_BILL_OF_MATERIAL\":null,\"EXTERNAL_MERCHANDISE_CATEGORY\":null,\"ARTICLE_CATEGORY\":\"00\",\"ARTICLE_TAX_CLASSIFICATION\":\"A\",\"CONTENT_UNIT\":\"KG\",\"NET_CONTENTS\":1.000,\"COMPARISON_PRICE_UNIT\":1,\"GROSS_CONTENTS\":1.000,\"DANGEROUS_GOODS_INDICATOR\":null,\"DRUG_ID_NUMBER_DIN\":null,\"DUNS_SUFFIX\":null,\"TRAY_NUMBERS\":\"8P\",\"LABOUR_COMMODITY_CODE\":\"534\",\"SOAKER_PAD_QUANTITY\":\"03\",\"TARE_CODE\":\"10\",\"KOSHER\":null,\"CATCH_WEIGHT_ITEM\":null,\"DAYS_FOR_OLD_STOCK_CALCULATION\":0,\"NUTRITION_DATA_REQUIRED\":\"N\",\"WILL_BE_USED_AS_ITRADE_ITEMS\":\"N\",\"RECLAMATION_ITEM\":null,\"HAZARDOUS_ITEM\":null,\"CERTIFIED_ORGANIC\":null,\"RETAIL_PACK_QUANTITY\":\"000\",\"ALTERNATE_CONTENT\":0.000,\"ALTERNATE_CONTENT_UNIT\":null,\"CASE_SALES_PACK\":0,\"RSC_CREDIT_NON_RETURNABLE_FLAG\":null,\"ARTICLE_IDENTIFIER\":null,\"COST_CHANGE_DATE_OVERRIDE\":null,\"GLUTEN_FREE\":null,\"SCAN_BASED_TRADING_GROUP_ID\":null,\"IPG_CODE_VALUE\":\"0000\",\"PRECURSOR_IDENTIFIER\":null,\"ETHNIC_CODE\":null,\"HALAL\":null,\"ASSORTMENT_LIST_TYPE\":\"A\",\"ABC_INDICATOR\":null,\"ARTICLE_COUNTRY_OF_ORIGIN\":null,\"ARTICLE_REGION_OF_ORIGIN\":null,\"VALUATION_MARGIN\":0.00,\"MINIMUM_TEMPERATURE\":2.00,\"MAXIMUM_TEMPERATURE\":5.00,\"TEMPERATURE_UNIT\":\"C\",\"VALUATIONCLASS\":\"3100\",\"PURCHASEUNITOFMEASURE\":\"CS\",\"SALESUNITOFMEASURE\":\"KG\",\"PRIVATELABEL\":\"G\",\"SapCountrydescriptions\":[],\"SapRegiondescriptions\":[],\"SapPrivatelabeldescriptions\":[{\"LANGUAGE\":\"E\",\"DESCRIPTION\":\"STERLING SILVER\"},{\"LANGUAGE\":\"F\",\"DESCRIPTION\":\"STERLING SILVER\"}],\"SapHazardousitemdescriptions\":[],\"SapContainerdescriptions\":[],\"SapIngredients\":[],\"SapTemperaturedescriptions\":[{\"LANGUAGE\":\"E\",\"DESCRIPTION\":\"Chilled\"},{\"LANGUAGE\":\"F\",\"DESCRIPTION\":\"Chilled\"}]},\"SapRegionalbasicdata\":[{\"SALES_ORGANIZATION\":\"3000\",\"LABOUR_COMMODITY_CODE\":\"534\",\"SOAKER_PAD_QUANTITY\":\"03\",\"TARE_CODE\":\"10\",\"GLUTEN_FREE\":null,\"TRAY_NUMBERS\":\"8P\",\"CATCH_WEIGHT_ITEM\":null,\"COST_CHANGE_DATE_OVERRIDE\":null,\"RSC_CREDIT_NON_RETURNABLE_FLAG\":null,\"CANSELLWHOLESALE\":null,\"SapWholesaleuoms\":[],\"IS_SINGLE_PICK\":null}],\"SapDescriptions\":{\"REGION\":null,\"SapArticledescriptions\":[{\"LANGUAGE\":\"E\",\"VALUE\":\"FS SterlSil Cross Rb Steak Bnls 1X1KG\"},{\"LANGUAGE\":\"F\",\"VALUE\":\"STERLSIL BIFT COTE CROISEE MARINE 1\\/1KG\"}],\"SapWebdescriptions\":[],\"SapConsumerdescription\":{\"BRAND_EN\":\"Sterling Silver\",\"PRODUCT_EN\":\"Simmering Steak\",\"FLAVOR_EN\":\"Cross Rib Boneless Family Size\",\"SIZE_EN\":null,\"BRAND_FR\":\"Sterling Silver\",\"PRODUCT_FR\":\"Bifteck marine\",\"FLAVOR_FR\":\"Cote croisse desos\",\"SIZE_FR\":null},\"SapBranddescriptions\":[{\"LANGUAGE\":\"F\",\"UNITOFMEASURE\":\"KG\",\"DESCRIPTION\":\"STERLING SILVER\"}],\"SapLabeldescriptions\":[{\"LANGUAGE\":\"E\",\"UNITOFMEASURE\":\"KG\",\"DESCRIPTION\":\"FS SterlSil Cross Rib Steak\"},{\"LANGUAGE\":\"F\",\"UNITOFMEASURE\":\"CS\",\"DESCRIPTION\":\"STERLSIL BIFT COTE CROISEE MARINE\"},{\"LANGUAGE\":\"F\",\"UNITOFMEASURE\":\"KG\",\"DESCRIPTION\":\"STERLSIL BIFT COTE CROISEE MARINE\"}],\"SapTillreceiptdescriptions\":[{\"LANGUAGE\":\"E\",\"UNITOFMEASURE\":\"KG\",\"DESCRIPTION\":\"FS SS Cross Rib Stk\"},{\"LANGUAGE\":\"F\",\"UNITOFMEASURE\":\"CS\",\"DESCRIPTION\":\"SS BIFTECK COTE\"},{\"LANGUAGE\":\"F\",\"UNITOFMEASURE\":\"KG\",\"DESCRIPTION\":\"SS BIFTECK COTE\"}],\"SapQuebecscaledescriptions\":[],\"SapScaleline1descriptions\":[{\"LANGUAGE\":\"E\",\"UNITOFMEASURE\":\"KG\",\"DESCRIPTION\":\"Sterling Silver Cross Rib\"}],\"SapScaleline2descriptions\":[{\"LANGUAGE\":\"E\",\"UNITOFMEASURE\":\"KG\",\"DESCRIPTION\":\"Simmering Steak, Bnls\"}],\"SapScaleline3descriptions\":[{\"LANGUAGE\":\"E\",\"UNITOFMEASURE\":\"KG\",\"DESCRIPTION\":\"Family Size\"}]},\"SapUnitofmeasure\":[{\"REGION\":null,\"UNITOFMEASURE\":\"KG\",\"MAINUPC\":\"211904000007\",\"GLN\":\"0000000000000\",\"GTIN\":\"00000000000000\",\"UPC_TYPE\":\"UPC-A\",\"SapAdditionalupcs\":[{\"UPC\":\"11904\",\"SapPlumformatcodes\":[],\"SapMadeinprovinces\":[],\"UPC_TYPE\":\"PLU\"}],\"UNITDIMENSION\":\"CM\",\"UNITOFWEIGHT\":\"KG\",\"GROSSWEIGHT\":1.000,\"LENGTH\":5.000,\"WIDTH\":5.000,\"HEIGHT\":5.000,\"VOLUME\":125.000,\"VOLUMEUNIT\":\"CCM\",\"SapPlumformatcodes\":[{\"SALES_ORGANIZATION\":\"3000\",\"PLUMFORMATCODE\":\"02\"}],\"NUMERATOR\":1,\"DENOMENATOR\":1,\"SapMadeinprovinces\":[]},{\"REGION\":null,\"UNITOFMEASURE\":\"CS\",\"MAINUPC\":null,\"GLN\":\"0000000000000\",\"GTIN\":\"00000000000000\",\"UPC_TYPE\":null,\"SapAdditionalupcs\":[],\"UNITDIMENSION\":\"CM\",\"UNITOFWEIGHT\":\"KG\",\"GROSSWEIGHT\":1.000,\"LENGTH\":0.000,\"WIDTH\":0.000,\"HEIGHT\":0.000,\"VOLUME\":0.000,\"VOLUMEUNIT\":\"M3\",\"SapPlumformatcodes\":[],\"NUMERATOR\":1,\"DENOMENATOR\":1,\"SapMadeinprovinces\":[]}],\"SapPurchasing\":[{\"SALES_ORGANIZATION\":\"3000\",\"VENDOR_NUMBER\":\"0000213623\",\"PURCHASE_ORDER_UNIT_OF_MEASURE\":\"CS\",\"VENDOR_ARTICLE_NUMBER\":null,\"VENDOR_SUBRANGE\":null,\"REGULAR_VENDOR\":null,\"PURCHASING_ORGANIZATION\":\"3000\",\"PURCHASE_INFO_RECORD_CATEGORY\":\"0\",\"SITE_NUMBER\":null,\"PURCHASING_GROUP\":\"002\",\"CURRENCY\":\"CAD\",\"MINIMUM_PURCHASE_ORDER_QTY\":1.000,\"STANDARD_PURCHASE_ORDER_QTY\":1.000,\"PLANNED_DELIVERY_TIME_IN_DAYS\":0,\"OVERDELIVERY_TOLERANCE_LIMIT\":0.0,\"UNLIMITED_OVERDELIVERY_ALLOWED\":\"X\",\"UNDERDELIVERY_TOLERANCE_LIMIT\":99.9,\"NET_PRICE_IN_PURCH_INFO_RECORD\":0.01,\"PRICE_UNIT\":1,\"ORDER_PRICE_UNIT_PURCHASING\":\"KG\",\"BASED_INVOICE_VERIFICATION\":null,\"CONDITION_GROUP_WITH_VENDOR\":null,\"SETTLEMENT_GROUP_1_PURCHASING\":null,\"SHIPPING_INSTRUCTIONS\":null,\"CONFIRMATION_CONTROL_KEY\":null,\"PRICE_DETERMINATION_DATE_CTRL\":\"1\",\"INCOTERMS_PART_1\":null,\"INCOTERMS_PART_2\":null,\"NO_EVALUATED_RECEIPTSETTLEMENT\":null,\"SETTLEMENT_GROUP_2\":null,\"SETTLEMENT_GROUP_3\":null,\"NOT_RELEVANT_SUBSEQ_SETTLEMENT\":null,\"ROUNDING_PROFILE\":null,\"UNIT_OF_MEASURE_GROUP\":null}],\"SapSourcing\":[{\"SALES_ORGANIZATION\":\"3000\",\"SITE\":\"0321\",\"SOURCE_LIST_RECORD_VALID_FROM\":\"2016-11-12\",\"SOURCE_LIST_RECORD_VALID_TO\":\"9999-12-31\",\"VENDOR_ACCOUNT_NUMBER\":\"0000213623\",\"INDICATOR_FIXED_VENDOR\":\"X\",\"PURCHASING_ORGANIZATION\":\"3000\"},{\"SALES_ORGANIZATION\":\"3000\",\"SITE\":\"0328\",\"SOURCE_LIST_RECORD_VALID_FROM\":\"2016-11-12\",\"SOURCE_LIST_RECORD_VALID_TO\":\"9999-12-31\",\"VENDOR_ACCOUNT_NUMBER\":\"0000213623\",\"INDICATOR_FIXED_VENDOR\":\"X\",\"PURCHASING_ORGANIZATION\":\"3000\"},{\"SALES_ORGANIZATION\":\"3000\",\"SITE\":\"0349\",\"SOURCE_LIST_RECORD_VALID_FROM\":\"2016-11-12\",\"SOURCE_LIST_RECORD_VALID_TO\":\"9999-12-31\",\"VENDOR_ACCOUNT_NUMBER\":\"0000213623\",\"INDICATOR_FIXED_VENDOR\":\"X\",\"PURCHASING_ORGANIZATION\":\"3000\"},{\"SALES_ORGANIZATION\":\"3000\",\"SITE\":\"0370\",\"SOURCE_LIST_RECORD_VALID_FROM\":\"2016-11-12\",\"SOURCE_LIST_RECORD_VALID_TO\":\"9999-12-31\",\"VENDOR_ACCOUNT_NUMBER\":\"0000213623\",\"INDICATOR_FIXED_VENDOR\":\"X\",\"PURCHASING_ORGANIZATION\":\"3000\"},{\"SALES_ORGANIZATION\":\"3000\",\"SITE\":\"0495\",\"SOURCE_LIST_RECORD_VALID_FROM\":\"2016-11-12\",\"SOURCE_LIST_RECORD_VALID_TO\":\"9999-12-31\",\"VENDOR_ACCOUNT_NUMBER\":\"0000213623\",\"INDICATOR_FIXED_VENDOR\":\"X\",\"PURCHASING_ORGANIZATION\":\"3000\"},{\"SALES_ORGANIZATION\":\"3000\",\"SITE\":\"0548\",\"SOURCE_LIST_RECORD_VALID_FROM\":\"2016-11-12\",\"SOURCE_LIST_RECORD_VALID_TO\":\"9999-12-31\",\"VENDOR_ACCOUNT_NUMBER\":\"0000213623\",\"INDICATOR_FIXED_VENDOR\":\"X\",\"PURCHASING_ORGANIZATION\":\"3000\"},{\"SALES_ORGANIZATION\":\"3000\",\"SITE\":\"0554\",\"SOURCE_LIST_RECORD_VALID_FROM\":\"2016-11-12\",\"SOURCE_LIST_RECORD_VALID_TO\":\"9999-12-31\",\"VENDOR_ACCOUNT_NUMBER\":\"0000213623\",\"INDICATOR_FIXED_VENDOR\":\"X\",\"PURCHASING_ORGANIZATION\":\"3000\"},{\"SALES_ORGANIZATION\":\"3000\",\"SITE\":\"0580\",\"SOURCE_LIST_RECORD_VALID_FROM\":\"2016-11-12\",\"SOURCE_LIST_RECORD_VALID_TO\":\"9999-12-31\",\"VENDOR_ACCOUNT_NUMBER\":\"0000213623\",\"INDICATOR_FIXED_VENDOR\":\"X\",\"PURCHASING_ORGANIZATION\":\"3000\"},{\"SALES_ORGANIZATION\":\"3000\",\"SITE\":\"0590\",\"SOURCE_LIST_RECORD_VALID_FROM\":\"2016-11-12\",\"SOURCE_LIST_RECORD_VALID_TO\":\"9999-12-31\",\"VENDOR_ACCOUNT_NUMBER\":\"0000213623\",\"INDICATOR_FIXED_VENDOR\":\"X\",\"PURCHASING_ORGANIZATION\":\"3000\"},{\"SALES_ORGANIZATION\":\"3000\",\"SITE\":\"0622\",\"SOURCE_LIST_RECORD_VALID_FROM\":\"2016-11-12\",\"SOURCE_LIST_RECORD_VALID_TO\":\"9999-12-31\",\"VENDOR_ACCOUNT_NUMBER\":\"0000213623\",\"INDICATOR_FIXED_VENDOR\":\"X\",\"PURCHASING_ORGANIZATION\":\"3000\"},{\"SALES_ORGANIZATION\":\"3000\",\"SITE\":\"0628\",\"SOURCE_LIST_RECORD_VALID_FROM\":\"2016-11-12\",\"SOURCE_LIST_RECORD_VALID_TO\":\"9999-12-31\",\"VENDOR_ACCOUNT_NUMBER\":\"0000213623\",\"INDICATOR_FIXED_VENDOR\":\"X\",\"PURCHASING_ORGANIZATION\":\"3000\"},{\"SALES_ORGANIZATION\":\"3000\",\"SITE\":\"0630\",\"SOURCE_LIST_RECORD_VALID_FROM\":\"2016-11-12\",\"SOURCE_LIST_RECORD_VALID_TO\":\"9999-12-31\",\"VENDOR_ACCOUNT_NUMBER\":\"0000213623\",\"INDICATOR_FIXED_VENDOR\":\"X\",\"PURCHASING_ORGANIZATION\":\"3000\"},{\"SALES_ORGANIZATION\":\"3000\",\"SITE\":\"0644\",\"SOURCE_LIST_RECORD_VALID_FROM\":\"2016-11-12\",\"SOURCE_LIST_RECORD_VALID_TO\":\"9999-12-31\",\"VENDOR_ACCOUNT_NUMBER\":\"0000213623\",\"INDICATOR_FIXED_VENDOR\":\"X\",\"PURCHASING_ORGANIZATION\":\"3000\"},{\"SALES_ORGANIZATION\":\"3000\",\"SITE\":\"0670\",\"SOURCE_LIST_RECORD_VALID_FROM\":\"2016-11-12\",\"SOURCE_LIST_RECORD_VALID_TO\":\"9999-12-31\",\"VENDOR_ACCOUNT_NUMBER\":\"0000213623\",\"INDICATOR_FIXED_VENDOR\":\"X\",\"PURCHASING_ORGANIZATION\":\"3000\"},{\"SALES_ORGANIZATION\":\"3000\",\"SITE\":\"0684\",\"SOURCE_LIST_RECORD_VALID_FROM\":\"2016-11-12\",\"SOURCE_LIST_RECORD_VALID_TO\":\"9999-12-31\",\"VENDOR_ACCOUNT_NUMBER\":\"0000213623\",\"INDICATOR_FIXED_VENDOR\":\"X\",\"PURCHASING_ORGANIZATION\":\"3000\"},{\"SALES_ORGANIZATION\":\"3000\",\"SITE\":\"0725\",\"SOURCE_LIST_RECORD_VALID_FROM\":\"2016-11-12\",\"SOURCE_LIST_RECORD_VALID_TO\":\"9999-12-31\",\"VENDOR_ACCOUNT_NUMBER\":\"0000213623\",\"INDICATOR_FIXED_VENDOR\":\"X\",\"PURCHASING_ORGANIZATION\":\"3000\"},{\"SALES_ORGANIZATION\":\"3000\",\"SITE\":\"0744\",\"SOURCE_LIST_RECORD_VALID_FROM\":\"2016-11-12\",\"SOURCE_LIST_RECORD_VALID_TO\":\"9999-12-31\",\"VENDOR_ACCOUNT_NUMBER\":\"0000213623\",\"INDICATOR_FIXED_VENDOR\":\"X\",\"PURCHASING_ORGANIZATION\":\"3000\"},{\"SALES_ORGANIZATION\":\"3000\",\"SITE\":\"0758\",\"SOURCE_LIST_RECORD_VALID_FROM\":\"2016-11-12\",\"SOURCE_LIST_RECORD_VALID_TO\":\"9999-12-31\",\"VENDOR_ACCOUNT_NUMBER\":\"0000213623\",\"INDICATOR_FIXED_VENDOR\":\"X\",\"PURCHASING_ORGANIZATION\":\"3000\"},{\"SALES_ORGANIZATION\":\"3000\",\"SITE\":\"0772\",\"SOURCE_LIST_RECORD_VALID_FROM\":\"2016-11-12\",\"SOURCE_LIST_RECORD_VALID_TO\":\"9999-12-31\",\"VENDOR_ACCOUNT_NUMBER\":\"0000213623\",\"INDICATOR_FIXED_VENDOR\":\"X\",\"PURCHASING_ORGANIZATION\":\"3000\"},{\"SALES_ORGANIZATION\":\"3000\",\"SITE\":\"0776\",\"SOURCE_LIST_RECORD_VALID_FROM\":\"2016-11-12\",\"SOURCE_LIST_RECORD_VALID_TO\":\"9999-12-31\",\"VENDOR_ACCOUNT_NUMBER\":\"0000213623\",\"INDICATOR_FIXED_VENDOR\":\"X\",\"PURCHASING_ORGANIZATION\":\"3000\"},{\"SALES_ORGANIZATION\":\"3000\",\"SITE\":\"0778\",\"SOURCE_LIST_RECORD_VALID_FROM\":\"2016-11-12\",\"SOURCE_LIST_RECORD_VALID_TO\":\"9999-12-31\",\"VENDOR_ACCOUNT_NUMBER\":\"0000213623\",\"INDICATOR_FIXED_VENDOR\":\"X\",\"PURCHASING_ORGANIZATION\":\"3000\"},{\"SALES_ORGANIZATION\":\"3000\",\"SITE\":\"0806\",\"SOURCE_LIST_RECORD_VALID_FROM\":\"2016-11-12\",\"SOURCE_LIST_RECORD_VALID_TO\":\"9999-12-31\",\"VENDOR_ACCOUNT_NUMBER\":\"0000213623\",\"INDICATOR_FIXED_VENDOR\":\"X\",\"PURCHASING_ORGANIZATION\":\"3000\"},{\"SALES_ORGANIZATION\":\"3000\",\"SITE\":\"0855\",\"SOURCE_LIST_RECORD_VALID_FROM\":\"2016-11-12\",\"SOURCE_LIST_RECORD_VALID_TO\":\"9999-12-31\",\"VENDOR_ACCOUNT_NUMBER\":\"0000213623\",\"INDICATOR_FIXED_VENDOR\":\"X\",\"PURCHASING_ORGANIZATION\":\"3000\"},{\"SALES_ORGANIZATION\":\"3000\",\"SITE\":\"0881\",\"SOURCE_LIST_RECORD_VALID_FROM\":\"2016-11-12\",\"SOURCE_LIST_RECORD_VALID_TO\":\"9999-12-31\",\"VENDOR_ACCOUNT_NUMBER\":\"0000213623\",\"INDICATOR_FIXED_VENDOR\":\"X\",\"PURCHASING_ORGANIZATION\":\"3000\"}],\"SapStores\":[{\"SALES_ORGANIZATION\":\"3000\",\"REGION\":\"NS\",\"SITE_NUMBER\":\"0321\",\"SITENAME\":\"Sobeys Spryfield\",\"SALESORGANIZATION\":\"3000\",\"PURCHASINGORGANIZATION\":\"3000\",\"DISTRIBUTIONCHANNEL\":\"48\",\"PURCHASING_GROUP\":\"002\",\"UNIT_OF_ISSUE\":\"KG\",\"ARTICLE_RP_PROFILE\":null,\"RP_TYPE\":\"ND\",\"STOCK_PLANNER_ARTICLES_PLANNER\":\"001\",\"PLANNED_DELIVERY_TIME_IN_DAYS\":0,\"PERIOD_INDICATOR\":\"T\",\"REORDER_POINT\":0.000,\"SAFETY_STOCK\":0.000,\"MAXIMUM_STOCK_LEVEL\":0.000,\"MAXIMUM_STORAGE_PERIOD\":5,\"MAXIMUM_STORAGE_PERIOD_UNIT\":\"10\",\"LOADING_GROUP\":\"0002\",\"QUOTA_ARRANGEMENT_USAGE\":null,\"GROUP_FOR_AVAILABILITY_CHECK\":\"KP\",\"SOURCE_OF_SUPPLY\":\"3\",\"COUNTRY_OF_ORIGIN\":null,\"PPC_PLANNING_CALENDAR\":null,\"PLANNING_CYCLE\":null,\"DEFAULT_STORAGE_LOCATION\":\"0001\",\"UNIT_OF_MEASURE_GROUP\":null,\"HANDLING_GROUP_WORKLOAD_CALC\":null,\"EXCLUDED_FROM_MINIMUM\":null,\"LABEL_QUANTITY\":\"01\",\"POS_AGE_VERIFY\":null,\"POS_ITEM_RESTRICT_CODE\":null,\"PRICE_REQUIRED\":null,\"PRODUCT_GRADE\":\"000\",\"QUANTITY_REQUIRED\":null,\"SIGNS_LABELS\":\"10\",\"VISUAL_VERIFY\":null,\"A_48_HOUR_PRODUCT\":null,\"PRORATION_QTY_LIMIT\":0,\"PROFIT_CENTER\":\"0321-001\",\"PROFIT_CENTER_DESCR_EN\":\"Spryfield Meat\",\"PROFIT_CENTER_DESCR_FR\":null,\"FORECAST_PROFILE\":null,\"FORECAST_MODEL\":null,\"REFERENCEARTICLECONSUMPTIONDT\":\"0000-00-00\",\"REFARTCONSUMPTIONMULTIPLIER\":0.00,\"REFERENCEARTICLEFORCONSUMPTION\":null,\"DISCOUNT_FLAG\":\"Y\",\"ASSORTMENT\":\"0000000321\",\"VALID_TO_DATE\":\"9999-12-31\",\"VALID_FROM_DATE\":\"2012-04-26\",\"POSDEPARTMENTNUMBER\":\"001\",\"MINIMUMSHELFLIFE\":\"000000\",\"MAXIMUMSHELFLIFE\":\"000000\",\"MINIMUNACCEPTED\":\"000000\",\"CUSTOMERSHELFLIFE\":\"000000\",\"OSPRETAILERREGIONID\":\"ISF_NS01\",\"LOCATIONID\":\"11560\",\"SapInstorelocations\":[{\"UPC\":\"11904\",\"UNITOFMEASURE\":\"KG\",\"AISLE\":\"70\",\"AISLETYPE\":\"A\",\"SIDE\":\"L\",\"AISLESECTION\":\"00\",\"SHELF\":null,\"HASSALES\":null},{\"UPC\":\"21190400000\",\"UNITOFMEASURE\":\"KG\",\"AISLE\":\"70\",\"AISLETYPE\":\"A\",\"SIDE\":\"L\",\"AISLESECTION\":\"00\",\"SHELF\":null,\"HASSALES\":null}],\"PRIMARYVENDOR\":\"0000213623\",\"LOTSIZE\":null,\"ROUNDINGVALUE\":0.000,\"SITE_STATUS\":null},{\"SALES_ORGANIZATION\":\"3000\",\"REGION\":\"NS\",\"SITE_NUMBER\":\"0328\",\"SITENAME\":\"Sobeys Glace Bay Reserve St\",\"SALESORGANIZATION\":\"3000\",\"PURCHASINGORGANIZATION\":\"3000\",\"DISTRIBUTIONCHANNEL\":\"48\",\"PURCHASING_GROUP\":\"002\",\"UNIT_OF_ISSUE\":\"KG\",\"ARTICLE_RP_PROFILE\":null,\"RP_TYPE\":\"ND\",\"STOCK_PLANNER_ARTICLES_PLANNER\":\"001\",\"PLANNED_DELIVERY_TIME_IN_DAYS\":0,\"PERIOD_INDICATOR\":\"T\",\"REORDER_POINT\":0.000,\"SAFETY_STOCK\":0.000,\"MAXIMUM_STOCK_LEVEL\":0.000,\"MAXIMUM_STORAGE_PERIOD\":5,\"MAXIMUM_STORAGE_PERIOD_UNIT\":\"10\",\"LOADING_GROUP\":\"0002\",\"QUOTA_ARRANGEMENT_USAGE\":null,\"GROUP_FOR_AVAILABILITY_CHECK\":\"KP\",\"SOURCE_OF_SUPPLY\":\"3\",\"COUNTRY_OF_ORIGIN\":null,\"PPC_PLANNING_CALENDAR\":null,\"PLANNING_CYCLE\":null,\"DEFAULT_STORAGE_LOCATION\":\"0001\",\"UNIT_OF_MEASURE_GROUP\":null,\"HANDLING_GROUP_WORKLOAD_CALC\":null,\"EXCLUDED_FROM_MINIMUM\":null,\"LABEL_QUANTITY\":\"01\",\"POS_AGE_VERIFY\":null,\"POS_ITEM_RESTRICT_CODE\":null,\"PRICE_REQUIRED\":null,\"PRODUCT_GRADE\":\"000\",\"QUANTITY_REQUIRED\":null,\"SIGNS_LABELS\":\"10\",\"VISUAL_VERIFY\":null,\"A_48_HOUR_PRODUCT\":null,\"PRORATION_QTY_LIMIT\":0,\"PROFIT_CENTER\":\"0328-001\",\"PROFIT_CENTER_DESCR_EN\":\"GlaceBay Meat\",\"PROFIT_CENTER_DESCR_FR\":null,\"FORECAST_PROFILE\":null,\"FORECAST_MODEL\":null,\"REFERENCEARTICLECONSUMPTIONDT\":\"0000-00-00\",\"REFARTCONSUMPTIONMULTIPLIER\":0.00,\"REFERENCEARTICLEFORCONSUMPTION\":null,\"DISCOUNT_FLAG\":\"Y\",\"ASSORTMENT\":\"0000000328\",\"VALID_TO_DATE\":\"9999-12-31\",\"VALID_FROM_DATE\":\"2012-04-26\",\"POSDEPARTMENTNUMBER\":\"001\",\"MINIMUMSHELFLIFE\":\"000000\",\"MAXIMUMSHELFLIFE\":\"000000\",\"MINIMUNACCEPTED\":\"000000\",\"CUSTOMERSHELFLIFE\":\"000000\",\"OSPRETAILERREGIONID\":\"ISF_NS03\",\"LOCATIONID\":\"11522\",\"SapInstorelocations\":[{\"UPC\":\"11904\",\"UNITOFMEASURE\":\"KG\",\"AISLE\":\"70\",\"AISLETYPE\":\"A\",\"SIDE\":null,\"AISLESECTION\":\"00\",\"SHELF\":null,\"HASSALES\":null},{\"UPC\":\"21190400000\",\"UNITOFMEASURE\":\"KG\",\"AISLE\":\"00\",\"AISLETYPE\":null,\"SIDE\":null,\"AISLESECTION\":\"00\",\"SHELF\":null,\"HASSALES\":\"X\"}],\"PRIMARYVENDOR\":\"0000213623\",\"LOTSIZE\":null,\"ROUNDINGVALUE\":0.000,\"SITE_STATUS\":null},{\"SALES_ORGANIZATION\":\"3000\",\"REGION\":\"NB\",\"SITE_NUMBER\":\"0349\",\"SITENAME\":\"Sobeys Brookside Mall\",\"SALESORGANIZATION\":\"3000\",\"PURCHASINGORGANIZATION\":\"3000\",\"DISTRIBUTIONCHANNEL\":\"48\",\"PURCHASING_GROUP\":\"002\",\"UNIT_OF_ISSUE\":\"KG\",\"ARTICLE_RP_PROFILE\":null,\"RP_TYPE\":\"ND\",\"STOCK_PLANNER_ARTICLES_PLANNER\":\"001\",\"PLANNED_DELIVERY_TIME_IN_DAYS\":0,\"PERIOD_INDICATOR\":\"T\",\"REORDER_POINT\":0.000,\"SAFETY_STOCK\":0.000,\"MAXIMUM_STOCK_LEVEL\":0.000,\"MAXIMUM_STORAGE_PERIOD\":5,\"MAXIMUM_STORAGE_PERIOD_UNIT\":\"10\",\"LOADING_GROUP\":\"0002\",\"QUOTA_ARRANGEMENT_USAGE\":null,\"GROUP_FOR_AVAILABILITY_CHECK\":\"KP\",\"SOURCE_OF_SUPPLY\":\"3\",\"COUNTRY_OF_ORIGIN\":null,\"PPC_PLANNING_CALENDAR\":null,\"PLANNING_CYCLE\":null,\"DEFAULT_STORAGE_LOCATION\":\"0001\",\"UNIT_OF_MEASURE_GROUP\":null,\"HANDLING_GROUP_WORKLOAD_CALC\":null,\"EXCLUDED_FROM_MINIMUM\":null,\"LABEL_QUANTITY\":\"01\",\"POS_AGE_VERIFY\":null,\"POS_ITEM_RESTRICT_CODE\":null,\"PRICE_REQUIRED\":null,\"PRODUCT_GRADE\":\"000\",\"QUANTITY_REQUIRED\":null,\"SIGNS_LABELS\":\"10\",\"VISUAL_VERIFY\":null,\"A_48_HOUR_PRODUCT\":null,\"PRORATION_QTY_LIMIT\":0,\"PROFIT_CENTER\":\"0349-001\",\"PROFIT_CENTER_DESCR_EN\":\"Brookside Meat\",\"PROFIT_CENTER_DESCR_FR\":null,\"FORECAST_PROFILE\":null,\"FORECAST_MODEL\":null,\"REFERENCEARTICLECONSUMPTIONDT\":\"0000-00-00\",\"REFARTCONSUMPTIONMULTIPLIER\":0.00,\"REFERENCEARTICLEFORCONSUMPTION\":null,\"DISCOUNT_FLAG\":\"Y\",\"ASSORTMENT\":\"0000000349\",\"VALID_TO_DATE\":\"9999-12-31\",\"VALID_FROM_DATE\":\"2012-04-26\",\"POSDEPARTMENTNUMBER\":\"001\",\"MINIMUMSHELFLIFE\":\"000000\",\"MAXIMUMSHELFLIFE\":\"000000\",\"MINIMUNACCEPTED\":\"000000\",\"CUSTOMERSHELFLIFE\":\"000000\",\"OSPRETAILERREGIONID\":\"ISF_NB01\",\"LOCATIONID\":\"11520\",\"SapInstorelocations\":[{\"UPC\":\"11904\",\"UNITOFMEASURE\":\"KG\",\"AISLE\":\"33\",\"AISLETYPE\":\"A\",\"SIDE\":null,\"AISLESECTION\":\"00\",\"SHELF\":null,\"HASSALES\":null},{\"UPC\":\"21190400000\",\"UNITOFMEASURE\":\"KG\",\"AISLE\":\"33\",\"AISLETYPE\":\"A\",\"SIDE\":null,\"AISLESECTION\":\"00\",\"SHELF\":null,\"HASSALES\":\"X\"}],\"PRIMARYVENDOR\":\"0000213623\",\"LOTSIZE\":null,\"ROUNDINGVALUE\":0.000,\"SITE_STATUS\":null},{\"SALES_ORGANIZATION\":\"3000\",\"REGION\":\"NS\",\"SITE_NUMBER\":\"0370\",\"SITENAME\":\"Sobeys Aberdeen Mall\",\"SALESORGANIZATION\":\"3000\",\"PURCHASINGORGANIZATION\":\"3000\",\"DISTRIBUTIONCHANNEL\":\"48\",\"PURCHASING_GROUP\":\"002\",\"UNIT_OF_ISSUE\":\"KG\",\"ARTICLE_RP_PROFILE\":null,\"RP_TYPE\":\"ND\",\"STOCK_PLANNER_ARTICLES_PLANNER\":\"001\",\"PLANNED_DELIVERY_TIME_IN_DAYS\":0,\"PERIOD_INDICATOR\":\"T\",\"REORDER_POINT\":0.000,\"SAFETY_STOCK\":0.000,\"MAXIMUM_STOCK_LEVEL\":0.000,\"MAXIMUM_STORAGE_PERIOD\":5,\"MAXIMUM_STORAGE_PERIOD_UNIT\":\"10\",\"LOADING_GROUP\":\"0002\",\"QUOTA_ARRANGEMENT_USAGE\":null,\"GROUP_FOR_AVAILABILITY_CHECK\":\"KP\",\"SOURCE_OF_SUPPLY\":\"3\",\"COUNTRY_OF_ORIGIN\":null,\"PPC_PLANNING_CALENDAR\":null,\"PLANNING_CYCLE\":null,\"DEFAULT_STORAGE_LOCATION\":\"0001\",\"UNIT_OF_MEASURE_GROUP\":null,\"HANDLING_GROUP_WORKLOAD_CALC\":null,\"EXCLUDED_FROM_MINIMUM\":null,\"LABEL_QUANTITY\":\"01\",\"POS_AGE_VERIFY\":null,\"POS_ITEM_RESTRICT_CODE\":null,\"PRICE_REQUIRED\":null,\"PRODUCT_GRADE\":\"000\",\"QUANTITY_REQUIRED\":null,\"SIGNS_LABELS\":\"10\",\"VISUAL_VERIFY\":null,\"A_48_HOUR_PRODUCT\":null,\"PRORATION_QTY_LIMIT\":0,\"PROFIT_CENTER\":\"0370-001\",\"PROFIT_CENTER_DESCR_EN\":\"Aberdeen Meat\",\"PROFIT_CENTER_DESCR_FR\":null,\"FORECAST_PROFILE\":null,\"FORECAST_MODEL\":null,\"REFERENCEARTICLECONSUMPTIONDT\":\"0000-00-00\",\"REFARTCONSUMPTIONMULTIPLIER\":0.00,\"REFERENCEARTICLEFORCONSUMPTION\":null,\"DISCOUNT_FLAG\":\"Y\",\"ASSORTMENT\":\"0000000370\",\"VALID_TO_DATE\":\"9999-12-31\",\"VALID_FROM_DATE\":\"2012-04-26\",\"POSDEPARTMENTNUMBER\":\"001\",\"MINIMUMSHELFLIFE\":\"000000\",\"MAXIMUMSHELFLIFE\":\"000000\",\"MINIMUNACCEPTED\":\"000000\",\"CUSTOMERSHELFLIFE\":\"000000\",\"OSPRETAILERREGIONID\":\"ISF_NS01\",\"LOCATIONID\":\"11545\",\"SapInstorelocations\":[{\"UPC\":\"11904\",\"UNITOFMEASURE\":\"KG\",\"AISLE\":\"27\",\"AISLETYPE\":\"A\",\"SIDE\":null,\"AISLESECTION\":\"00\",\"SHELF\":null,\"HASSALES\":null},{\"UPC\":\"21190400000\",\"UNITOFMEASURE\":\"KG\",\"AISLE\":\"27\",\"AISLETYPE\":\"A\",\"SIDE\":null,\"AISLESECTION\":\"00\",\"SHELF\":null,\"HASSALES\":null}],\"PRIMARYVENDOR\":\"0000213623\",\"LOTSIZE\":null,\"ROUNDINGVALUE\":0.000,\"SITE_STATUS\":null},{\"SALES_ORGANIZATION\":\"3000\",\"REGION\":\"NB\",\"SITE_NUMBER\":\"0495\",\"SITENAME\":\"Sobeys Rothesay\",\"SALESORGANIZATION\":\"3000\",\"PURCHASINGORGANIZATION\":\"3000\",\"DISTRIBUTIONCHANNEL\":\"48\",\"PURCHASING_GROUP\":\"002\",\"UNIT_OF_ISSUE\":\"KG\",\"ARTICLE_RP_PROFILE\":null,\"RP_TYPE\":\"ND\",\"STOCK_PLANNER_ARTICLES_PLANNER\":\"001\",\"PLANNED_DELIVERY_TIME_IN_DAYS\":0,\"PERIOD_INDICATOR\":\"T\",\"REORDER_POINT\":0.000,\"SAFETY_STOCK\":0.000,\"MAXIMUM_STOCK_LEVEL\":0.000,\"MAXIMUM_STORAGE_PERIOD\":5,\"MAXIMUM_STORAGE_PERIOD_UNIT\":\"10\",\"LOADING_GROUP\":\"0002\",\"QUOTA_ARRANGEMENT_USAGE\":null,\"GROUP_FOR_AVAILABILITY_CHECK\":\"KP\",\"SOURCE_OF_SUPPLY\":\"3\",\"COUNTRY_OF_ORIGIN\":null,\"PPC_PLANNING_CALENDAR\":null,\"PLANNING_CYCLE\":null,\"DEFAULT_STORAGE_LOCATION\":\"0001\",\"UNIT_OF_MEASURE_GROUP\":null,\"HANDLING_GROUP_WORKLOAD_CALC\":null,\"EXCLUDED_FROM_MINIMUM\":null,\"LABEL_QUANTITY\":\"01\",\"POS_AGE_VERIFY\":null,\"POS_ITEM_RESTRICT_CODE\":null,\"PRICE_REQUIRED\":null,\"PRODUCT_GRADE\":\"000\",\"QUANTITY_REQUIRED\":null,\"SIGNS_LABELS\":\"10\",\"VISUAL_VERIFY\":null,\"A_48_HOUR_PRODUCT\":null,\"PRORATION_QTY_LIMIT\":0,\"PROFIT_CENTER\":\"0495-001\",\"PROFIT_CENTER_DESCR_EN\":\"Rothesay Meat\",\"PROFIT_CENTER_DESCR_FR\":null,\"FORECAST_PROFILE\":null,\"FORECAST_MODEL\":null,\"REFERENCEARTICLECONSUMPTIONDT\":\"0000-00-00\",\"REFARTCONSUMPTIONMULTIPLIER\":0.00,\"REFERENCEARTICLEFORCONSUMPTION\":null,\"DISCOUNT_FLAG\":\"Y\",\"ASSORTMENT\":\"0000000495\",\"VALID_TO_DATE\":\"9999-12-31\",\"VALID_FROM_DATE\":\"2012-04-26\",\"POSDEPARTMENTNUMBER\":\"001\",\"MINIMUMSHELFLIFE\":\"000000\",\"MAXIMUMSHELFLIFE\":\"000000\",\"MINIMUNACCEPTED\":\"000000\",\"CUSTOMERSHELFLIFE\":\"000000\",\"OSPRETAILERREGIONID\":\"ISF_NB01\",\"LOCATIONID\":\"11554\",\"SapInstorelocations\":[{\"UPC\":\"11904\",\"UNITOFMEASURE\":\"KG\",\"AISLE\":\"24\",\"AISLETYPE\":\"A\",\"SIDE\":null,\"AISLESECTION\":\"00\",\"SHELF\":null,\"HASSALES\":null},{\"UPC\":\"21190400000\",\"UNITOFMEASURE\":\"KG\",\"AISLE\":\"24\",\"AISLETYPE\":\"A\",\"SIDE\":null,\"AISLESECTION\":\"00\",\"SHELF\":null,\"HASSALES\":\"X\"}],\"PRIMARYVENDOR\":\"0000213623\",\"LOTSIZE\":null,\"ROUNDINGVALUE\":0.000,\"SITE_STATUS\":null},{\"SALES_ORGANIZATION\":\"3000\",\"REGION\":\"NB\",\"SITE_NUMBER\":\"0548\",\"SITENAME\":\"Sobeys East Point\",\"SALESORGANIZATION\":\"3000\",\"PURCHASINGORGANIZATION\":\"3000\",\"DISTRIBUTIONCHANNEL\":\"48\",\"PURCHASING_GROUP\":\"002\",\"UNIT_OF_ISSUE\":\"KG\",\"ARTICLE_RP_PROFILE\":null,\"RP_TYPE\":\"ND\",\"STOCK_PLANNER_ARTICLES_PLANNER\":\"001\",\"PLANNED_DELIVERY_TIME_IN_DAYS\":0,\"PERIOD_INDICATOR\":\"T\",\"REORDER_POINT\":0.000,\"SAFETY_STOCK\":0.000,\"MAXIMUM_STOCK_LEVEL\":0.000,\"MAXIMUM_STORAGE_PERIOD\":5,\"MAXIMUM_STORAGE_PERIOD_UNIT\":\"10\",\"LOADING_GROUP\":\"0002\",\"QUOTA_ARRANGEMENT_USAGE\":null,\"GROUP_FOR_AVAILABILITY_CHECK\":\"KP\",\"SOURCE_OF_SUPPLY\":\"3\",\"COUNTRY_OF_ORIGIN\":null,\"PPC_PLANNING_CALENDAR\":null,\"PLANNING_CYCLE\":null,\"DEFAULT_STORAGE_LOCATION\":\"0001\",\"UNIT_OF_MEASURE_GROUP\":null,\"HANDLING_GROUP_WORKLOAD_CALC\":null,\"EXCLUDED_FROM_MINIMUM\":null,\"LABEL_QUANTITY\":\"01\",\"POS_AGE_VERIFY\":null,\"POS_ITEM_RESTRICT_CODE\":null,\"PRICE_REQUIRED\":null,\"PRODUCT_GRADE\":\"000\",\"QUANTITY_REQUIRED\":null,\"SIGNS_LABELS\":\"10\",\"VISUAL_VERIFY\":null,\"A_48_HOUR_PRODUCT\":null,\"PRORATION_QTY_LIMIT\":0,\"PROFIT_CENTER\":\"0548-001\",\"PROFIT_CENTER_DESCR_EN\":\"Sobeys East Pt Meat\",\"PROFIT_CENTER_DESCR_FR\":null,\"FORECAST_PROFILE\":null,\"FORECAST_MODEL\":null,\"REFERENCEARTICLECONSUMPTIONDT\":\"0000-00-00\",\"REFARTCONSUMPTIONMULTIPLIER\":0.00,\"REFERENCEARTICLEFORCONSUMPTION\":null,\"DISCOUNT_FLAG\":\"Y\",\"ASSORTMENT\":\"0000000548\",\"VALID_TO_DATE\":\"9999-12-31\",\"VALID_FROM_DATE\":\"2016-05-02\",\"POSDEPARTMENTNUMBER\":\"001\",\"MINIMUMSHELFLIFE\":\"000000\",\"MAXIMUMSHELFLIFE\":\"000000\",\"MINIMUNACCEPTED\":\"000000\",\"CUSTOMERSHELFLIFE\":\"000000\",\"OSPRETAILERREGIONID\":\"ISF_NB01\",\"LOCATIONID\":\"22106\",\"SapInstorelocations\":[{\"UPC\":\"11904\",\"UNITOFMEASURE\":\"KG\",\"AISLE\":\"41\",\"AISLETYPE\":\"A\",\"SIDE\":null,\"AISLESECTION\":\"00\",\"SHELF\":null,\"HASSALES\":null},{\"UPC\":\"21190400000\",\"UNITOFMEASURE\":\"KG\",\"AISLE\":\"41\",\"AISLETYPE\":\"A\",\"SIDE\":null,\"AISLESECTION\":\"00\",\"SHELF\":null,\"HASSALES\":\"X\"}],\"PRIMARYVENDOR\":\"0000213623\",\"LOTSIZE\":null,\"ROUNDINGVALUE\":0.000,\"SITE_STATUS\":null},{\"SALES_ORGANIZATION\":\"3000\",\"REGION\":\"NS\",\"SITE_NUMBER\":\"0554\",\"SITENAME\":\"Sobeys Windsor Street\",\"SALESORGANIZATION\":\"3000\",\"PURCHASINGORGANIZATION\":\"3000\",\"DISTRIBUTIONCHANNEL\":\"48\",\"PURCHASING_GROUP\":\"002\",\"UNIT_OF_ISSUE\":\"KG\",\"ARTICLE_RP_PROFILE\":null,\"RP_TYPE\":\"ND\",\"STOCK_PLANNER_ARTICLES_PLANNER\":\"001\",\"PLANNED_DELIVERY_TIME_IN_DAYS\":0,\"PERIOD_INDICATOR\":\"T\",\"REORDER_POINT\":0.000,\"SAFETY_STOCK\":0.000,\"MAXIMUM_STOCK_LEVEL\":0.000,\"MAXIMUM_STORAGE_PERIOD\":5,\"MAXIMUM_STORAGE_PERIOD_UNIT\":\"10\",\"LOADING_GROUP\":\"0002\",\"QUOTA_ARRANGEMENT_USAGE\":null,\"GROUP_FOR_AVAILABILITY_CHECK\":\"KP\",\"SOURCE_OF_SUPPLY\":\"3\",\"COUNTRY_OF_ORIGIN\":null,\"PPC_PLANNING_CALENDAR\":null,\"PLANNING_CYCLE\":null,\"DEFAULT_STORAGE_LOCATION\":\"0001\",\"UNIT_OF_MEASURE_GROUP\":null,\"HANDLING_GROUP_WORKLOAD_CALC\":null,\"EXCLUDED_FROM_MINIMUM\":null,\"LABEL_QUANTITY\":\"01\",\"POS_AGE_VERIFY\":null,\"POS_ITEM_RESTRICT_CODE\":null,\"PRICE_REQUIRED\":null,\"PRODUCT_GRADE\":\"000\",\"QUANTITY_REQUIRED\":null,\"SIGNS_LABELS\":\"10\",\"VISUAL_VERIFY\":null,\"A_48_HOUR_PRODUCT\":null,\"PRORATION_QTY_LIMIT\":0,\"PROFIT_CENTER\":\"0554-001\",\"PROFIT_CENTER_DESCR_EN\":\"Windsor St Meat\",\"PROFIT_CENTER_DESCR_FR\":null,\"FORECAST_PROFILE\":null,\"FORECAST_MODEL\":null,\"REFERENCEARTICLECONSUMPTIONDT\":\"0000-00-00\",\"REFARTCONSUMPTIONMULTIPLIER\":0.00,\"REFERENCEARTICLEFORCONSUMPTION\":null,\"DISCOUNT_FLAG\":\"Y\",\"ASSORTMENT\":\"0000000554\",\"VALID_TO_DATE\":\"9999-12-31\",\"VALID_FROM_DATE\":\"2012-04-26\",\"POSDEPARTMENTNUMBER\":\"001\",\"MINIMUMSHELFLIFE\":\"000000\",\"MAXIMUMSHELFLIFE\":\"000000\",\"MINIMUNACCEPTED\":\"000000\",\"CUSTOMERSHELFLIFE\":\"000000\",\"OSPRETAILERREGIONID\":\"ISF_NS01\",\"LOCATIONID\":\"11528\",\"SapInstorelocations\":[{\"UPC\":\"11904\",\"UNITOFMEASURE\":\"KG\",\"AISLE\":\"00\",\"AISLETYPE\":null,\"SIDE\":null,\"AISLESECTION\":\"00\",\"SHELF\":null,\"HASSALES\":null},{\"UPC\":\"21190400000\",\"UNITOFMEASURE\":\"KG\",\"AISLE\":\"00\",\"AISLETYPE\":null,\"SIDE\":null,\"AISLESECTION\":\"00\",\"SHELF\":null,\"HASSALES\":\"X\"}],\"PRIMARYVENDOR\":\"0000213623\",\"LOTSIZE\":null,\"ROUNDINGVALUE\":0.000,\"SITE_STATUS\":null},{\"SALES_ORGANIZATION\":\"3000\",\"REGION\":\"NS\",\"SITE_NUMBER\":\"0580\",\"SITENAME\":\"Sobeys Bedford Mill Cove\",\"SALESORGANIZATION\":\"3000\",\"PURCHASINGORGANIZATION\":\"3000\",\"DISTRIBUTIONCHANNEL\":\"48\",\"PURCHASING_GROUP\":\"002\",\"UNIT_OF_ISSUE\":\"KG\",\"ARTICLE_RP_PROFILE\":null,\"RP_TYPE\":\"ND\",\"STOCK_PLANNER_ARTICLES_PLANNER\":\"001\",\"PLANNED_DELIVERY_TIME_IN_DAYS\":0,\"PERIOD_INDICATOR\":\"T\",\"REORDER_POINT\":0.000,\"SAFETY_STOCK\":0.000,\"MAXIMUM_STOCK_LEVEL\":0.000,\"MAXIMUM_STORAGE_PERIOD\":5,\"MAXIMUM_STORAGE_PERIOD_UNIT\":\"10\",\"LOADING_GROUP\":\"0002\",\"QUOTA_ARRANGEMENT_USAGE\":null,\"GROUP_FOR_AVAILABILITY_CHECK\":\"KP\",\"SOURCE_OF_SUPPLY\":\"3\",\"COUNTRY_OF_ORIGIN\":null,\"PPC_PLANNING_CALENDAR\":null,\"PLANNING_CYCLE\":null,\"DEFAULT_STORAGE_LOCATION\":\"0001\",\"UNIT_OF_MEASURE_GROUP\":null,\"HANDLING_GROUP_WORKLOAD_CALC\":null,\"EXCLUDED_FROM_MINIMUM\":null,\"LABEL_QUANTITY\":\"01\",\"POS_AGE_VERIFY\":null,\"POS_ITEM_RESTRICT_CODE\":null,\"PRICE_REQUIRED\":null,\"PRODUCT_GRADE\":\"000\",\"QUANTITY_REQUIRED\":null,\"SIGNS_LABELS\":\"10\",\"VISUAL_VERIFY\":null,\"A_48_HOUR_PRODUCT\":null,\"PRORATION_QTY_LIMIT\":0,\"PROFIT_CENTER\":\"0580-001\",\"PROFIT_CENTER_DESCR_EN\":\"Bedford Meat\",\"PROFIT_CENTER_DESCR_FR\":null,\"FORECAST_PROFILE\":null,\"FORECAST_MODEL\":null,\"REFERENCEARTICLECONSUMPTIONDT\":\"0000-00-00\",\"REFARTCONSUMPTIONMULTIPLIER\":0.00,\"REFERENCEARTICLEFORCONSUMPTION\":null,\"DISCOUNT_FLAG\":\"Y\",\"ASSORTMENT\":\"0000000580\",\"VALID_TO_DATE\":\"9999-12-31\",\"VALID_FROM_DATE\":\"2012-04-26\",\"POSDEPARTMENTNUMBER\":\"001\",\"MINIMUMSHELFLIFE\":\"000000\",\"MAXIMUMSHELFLIFE\":\"000000\",\"MINIMUNACCEPTED\":\"000000\",\"CUSTOMERSHELFLIFE\":\"000000\",\"OSPRETAILERREGIONID\":\"ISF_NS01\",\"LOCATIONID\":\"11500\",\"SapInstorelocations\":[{\"UPC\":\"11904\",\"UNITOFMEASURE\":\"KG\",\"AISLE\":\"22\",\"AISLETYPE\":\"A\",\"SIDE\":null,\"AISLESECTION\":\"00\",\"SHELF\":null,\"HASSALES\":null},{\"UPC\":\"21190400000\",\"UNITOFMEASURE\":\"KG\",\"AISLE\":\"00\",\"AISLETYPE\":null,\"SIDE\":null,\"AISLESECTION\":\"00\",\"SHELF\":null,\"HASSALES\":\"X\"}],\"PRIMARYVENDOR\":\"0000213623\",\"LOTSIZE\":null,\"ROUNDINGVALUE\":0.000,\"SITE_STATUS\":null},{\"SALES_ORGANIZATION\":\"3000\",\"REGION\":\"NL\",\"SITE_NUMBER\":\"0590\",\"SITENAME\":\"Sobeys Long Pond\",\"SALESORGANIZATION\":\"3000\",\"PURCHASINGORGANIZATION\":\"3000\",\"DISTRIBUTIONCHANNEL\":\"49\",\"PURCHASING_GROUP\":\"002\",\"UNIT_OF_ISSUE\":\"KG\",\"ARTICLE_RP_PROFILE\":null,\"RP_TYPE\":\"ND\",\"STOCK_PLANNER_ARTICLES_PLANNER\":\"001\",\"PLANNED_DELIVERY_TIME_IN_DAYS\":0,\"PERIOD_INDICATOR\":\"T\",\"REORDER_POINT\":0.000,\"SAFETY_STOCK\":0.000,\"MAXIMUM_STOCK_LEVEL\":0.000,\"MAXIMUM_STORAGE_PERIOD\":5,\"MAXIMUM_STORAGE_PERIOD_UNIT\":\"10\",\"LOADING_GROUP\":\"0002\",\"QUOTA_ARRANGEMENT_USAGE\":null,\"GROUP_FOR_AVAILABILITY_CHECK\":\"KP\",\"SOURCE_OF_SUPPLY\":\"3\",\"COUNTRY_OF_ORIGIN\":null,\"PPC_PLANNING_CALENDAR\":null,\"PLANNING_CYCLE\":null,\"DEFAULT_STORAGE_LOCATION\":\"0001\",\"UNIT_OF_MEASURE_GROUP\":null,\"HANDLING_GROUP_WORKLOAD_CALC\":null,\"EXCLUDED_FROM_MINIMUM\":null,\"LABEL_QUANTITY\":\"01\",\"POS_AGE_VERIFY\":null,\"POS_ITEM_RESTRICT_CODE\":null,\"PRICE_REQUIRED\":null,\"PRODUCT_GRADE\":\"000\",\"QUANTITY_REQUIRED\":null,\"SIGNS_LABELS\":\"10\",\"VISUAL_VERIFY\":null,\"A_48_HOUR_PRODUCT\":null,\"PRORATION_QTY_LIMIT\":0,\"PROFIT_CENTER\":\"0590-001\",\"PROFIT_CENTER_DESCR_EN\":\"Long Pond Meat\",\"PROFIT_CENTER_DESCR_FR\":null,\"FORECAST_PROFILE\":null,\"FORECAST_MODEL\":null,\"REFERENCEARTICLECONSUMPTIONDT\":\"0000-00-00\",\"REFARTCONSUMPTIONMULTIPLIER\":0.00,\"REFERENCEARTICLEFORCONSUMPTION\":null,\"DISCOUNT_FLAG\":\"Y\",\"ASSORTMENT\":\"0000000590\",\"VALID_TO_DATE\":\"9999-12-31\",\"VALID_FROM_DATE\":\"2012-04-26\",\"POSDEPARTMENTNUMBER\":\"001\",\"MINIMUMSHELFLIFE\":\"000000\",\"MAXIMUMSHELFLIFE\":\"000000\",\"MINIMUNACCEPTED\":\"000000\",\"CUSTOMERSHELFLIFE\":\"000000\",\"OSPRETAILERREGIONID\":\"ISF_NL01\",\"LOCATIONID\":\"11535\",\"SapInstorelocations\":[{\"UPC\":\"11904\",\"UNITOFMEASURE\":\"KG\",\"AISLE\":\"00\",\"AISLETYPE\":null,\"SIDE\":null,\"AISLESECTION\":\"00\",\"SHELF\":null,\"HASSALES\":null},{\"UPC\":\"21190400000\",\"UNITOFMEASURE\":\"KG\",\"AISLE\":\"00\",\"AISLETYPE\":null,\"SIDE\":null,\"AISLESECTION\":\"00\",\"SHELF\":null,\"HASSALES\":\"X\"}],\"PRIMARYVENDOR\":\"0000213623\",\"LOTSIZE\":null,\"ROUNDINGVALUE\":0.000,\"SITE_STATUS\":null},{\"SALES_ORGANIZATION\":\"3000\",\"REGION\":\"NS\",\"SITE_NUMBER\":\"0622\",\"SITENAME\":\"Sobeys Panavista Drive\",\"SALESORGANIZATION\":\"3000\",\"PURCHASINGORGANIZATION\":\"3000\",\"DISTRIBUTIONCHANNEL\":\"48\",\"PURCHASING_GROUP\":\"002\",\"UNIT_OF_ISSUE\":\"KG\",\"ARTICLE_RP_PROFILE\":null,\"RP_TYPE\":\"ND\",\"STOCK_PLANNER_ARTICLES_PLANNER\":\"001\",\"PLANNED_DELIVERY_TIME_IN_DAYS\":0,\"PERIOD_INDICATOR\":\"T\",\"REORDER_POINT\":0.000,\"SAFETY_STOCK\":0.000,\"MAXIMUM_STOCK_LEVEL\":0.000,\"MAXIMUM_STORAGE_PERIOD\":5,\"MAXIMUM_STORAGE_PERIOD_UNIT\":\"10\",\"LOADING_GROUP\":\"0002\",\"QUOTA_ARRANGEMENT_USAGE\":null,\"GROUP_FOR_AVAILABILITY_CHECK\":\"KP\",\"SOURCE_OF_SUPPLY\":\"3\",\"COUNTRY_OF_ORIGIN\":null,\"PPC_PLANNING_CALENDAR\":null,\"PLANNING_CYCLE\":null,\"DEFAULT_STORAGE_LOCATION\":\"0001\",\"UNIT_OF_MEASURE_GROUP\":null,\"HANDLING_GROUP_WORKLOAD_CALC\":null,\"EXCLUDED_FROM_MINIMUM\":null,\"LABEL_QUANTITY\":\"01\",\"POS_AGE_VERIFY\":null,\"POS_ITEM_RESTRICT_CODE\":null,\"PRICE_REQUIRED\":null,\"PRODUCT_GRADE\":\"000\",\"QUANTITY_REQUIRED\":null,\"SIGNS_LABELS\":\"10\",\"VISUAL_VERIFY\":null,\"A_48_HOUR_PRODUCT\":null,\"PRORATION_QTY_LIMIT\":0,\"PROFIT_CENTER\":\"0622-001\",\"PROFIT_CENTER_DESCR_EN\":\"Panavista Meat\",\"PROFIT_CENTER_DESCR_FR\":null,\"FORECAST_PROFILE\":null,\"FORECAST_MODEL\":null,\"REFERENCEARTICLECONSUMPTIONDT\":\"0000-00-00\",\"REFARTCONSUMPTIONMULTIPLIER\":0.00,\"REFERENCEARTICLEFORCONSUMPTION\":null,\"DISCOUNT_FLAG\":\"Y\",\"ASSORTMENT\":\"0000000622\",\"VALID_TO_DATE\":\"9999-12-31\",\"VALID_FROM_DATE\":\"2012-04-26\",\"POSDEPARTMENTNUMBER\":\"001\",\"MINIMUMSHELFLIFE\":\"000000\",\"MAXIMUMSHELFLIFE\":\"000000\",\"MINIMUNACCEPTED\":\"000000\",\"CUSTOMERSHELFLIFE\":\"000000\",\"OSPRETAILERREGIONID\":\"ISF_NS01\",\"LOCATIONID\":\"11512\",\"SapInstorelocations\":[{\"UPC\":\"11904\",\"UNITOFMEASURE\":\"KG\",\"AISLE\":\"70\",\"AISLETYPE\":\"A\",\"SIDE\":null,\"AISLESECTION\":\"00\",\"SHELF\":null,\"HASSALES\":null},{\"UPC\":\"21190400000\",\"UNITOFMEASURE\":\"KG\",\"AISLE\":\"70\",\"AISLETYPE\":\"A\",\"SIDE\":null,\"AISLESECTION\":\"00\",\"SHELF\":null,\"HASSALES\":\"X\"}],\"PRIMARYVENDOR\":\"0000213623\",\"LOTSIZE\":null,\"ROUNDINGVALUE\":0.000,\"SITE_STATUS\":null},{\"SALES_ORGANIZATION\":\"3000\",\"REGION\":\"PE\",\"SITE_NUMBER\":\"0628\",\"SITENAME\":\"Sobeys Babineau Drive\",\"SALESORGANIZATION\":\"3000\",\"PURCHASINGORGANIZATION\":\"3000\",\"DISTRIBUTIONCHANNEL\":\"48\",\"PURCHASING_GROUP\":\"002\",\"UNIT_OF_ISSUE\":\"KG\",\"ARTICLE_RP_PROFILE\":null,\"RP_TYPE\":\"ND\",\"STOCK_PLANNER_ARTICLES_PLANNER\":\"001\",\"PLANNED_DELIVERY_TIME_IN_DAYS\":0,\"PERIOD_INDICATOR\":\"T\",\"REORDER_POINT\":0.000,\"SAFETY_STOCK\":0.000,\"MAXIMUM_STOCK_LEVEL\":0.000,\"MAXIMUM_STORAGE_PERIOD\":5,\"MAXIMUM_STORAGE_PERIOD_UNIT\":\"10\",\"LOADING_GROUP\":\"0002\",\"QUOTA_ARRANGEMENT_USAGE\":null,\"GROUP_FOR_AVAILABILITY_CHECK\":\"KP\",\"SOURCE_OF_SUPPLY\":\"3\",\"COUNTRY_OF_ORIGIN\":null,\"PPC_PLANNING_CALENDAR\":null,\"PLANNING_CYCLE\":null,\"DEFAULT_STORAGE_LOCATION\":\"0001\",\"UNIT_OF_MEASURE_GROUP\":null,\"HANDLING_GROUP_WORKLOAD_CALC\":null,\"EXCLUDED_FROM_MINIMUM\":null,\"LABEL_QUANTITY\":\"01\",\"POS_AGE_VERIFY\":null,\"POS_ITEM_RESTRICT_CODE\":null,\"PRICE_REQUIRED\":null,\"PRODUCT_GRADE\":\"000\",\"QUANTITY_REQUIRED\":null,\"SIGNS_LABELS\":\"10\",\"VISUAL_VERIFY\":null,\"A_48_HOUR_PRODUCT\":null,\"PRORATION_QTY_LIMIT\":0,\"PROFIT_CENTER\":\"0628-001\",\"PROFIT_CENTER_DESCR_EN\":\"Babineau Dr Meat\",\"PROFIT_CENTER_DESCR_FR\":null,\"FORECAST_PROFILE\":null,\"FORECAST_MODEL\":null,\"REFERENCEARTICLECONSUMPTIONDT\":\"0000-00-00\",\"REFARTCONSUMPTIONMULTIPLIER\":0.00,\"REFERENCEARTICLEFORCONSUMPTION\":null,\"DISCOUNT_FLAG\":\"Y\",\"ASSORTMENT\":\"0000000628\",\"VALID_TO_DATE\":\"9999-12-31\",\"VALID_FROM_DATE\":\"2012-04-26\",\"POSDEPARTMENTNUMBER\":\"001\",\"MINIMUMSHELFLIFE\":\"000000\",\"MAXIMUMSHELFLIFE\":\"000000\",\"MINIMUNACCEPTED\":\"000000\",\"CUSTOMERSHELFLIFE\":\"000000\",\"OSPRETAILERREGIONID\":\"ISF_PE01\",\"LOCATIONID\":\"18684\",\"SapInstorelocations\":[{\"UPC\":\"11904\",\"UNITOFMEASURE\":\"KG\",\"AISLE\":\"00\",\"AISLETYPE\":null,\"SIDE\":null,\"AISLESECTION\":\"00\",\"SHELF\":null,\"HASSALES\":null},{\"UPC\":\"21190400000\",\"UNITOFMEASURE\":\"KG\",\"AISLE\":\"00\",\"AISLETYPE\":null,\"SIDE\":null,\"AISLESECTION\":\"00\",\"SHELF\":null,\"HASSALES\":null}],\"PRIMARYVENDOR\":\"0000213623\",\"LOTSIZE\":null,\"ROUNDINGVALUE\":0.000,\"SITE_STATUS\":null},{\"SALES_ORGANIZATION\":\"3000\",\"REGION\":\"NS\",\"SITE_NUMBER\":\"0630\",\"SITENAME\":\"Sobeys Sydney River\",\"SALESORGANIZATION\":\"3000\",\"PURCHASINGORGANIZATION\":\"3000\",\"DISTRIBUTIONCHANNEL\":\"48\",\"PURCHASING_GROUP\":\"002\",\"UNIT_OF_ISSUE\":\"KG\",\"ARTICLE_RP_PROFILE\":null,\"RP_TYPE\":\"ND\",\"STOCK_PLANNER_ARTICLES_PLANNER\":\"001\",\"PLANNED_DELIVERY_TIME_IN_DAYS\":0,\"PERIOD_INDICATOR\":\"T\",\"REORDER_POINT\":0.000,\"SAFETY_STOCK\":0.000,\"MAXIMUM_STOCK_LEVEL\":0.000,\"MAXIMUM_STORAGE_PERIOD\":5,\"MAXIMUM_STORAGE_PERIOD_UNIT\":\"10\",\"LOADING_GROUP\":\"0002\",\"QUOTA_ARRANGEMENT_USAGE\":null,\"GROUP_FOR_AVAILABILITY_CHECK\":\"KP\",\"SOURCE_OF_SUPPLY\":\"3\",\"COUNTRY_OF_ORIGIN\":null,\"PPC_PLANNING_CALENDAR\":null,\"PLANNING_CYCLE\":null,\"DEFAULT_STORAGE_LOCATION\":\"0001\",\"UNIT_OF_MEASURE_GROUP\":null,\"HANDLING_GROUP_WORKLOAD_CALC\":null,\"EXCLUDED_FROM_MINIMUM\":null,\"LABEL_QUANTITY\":\"01\",\"POS_AGE_VERIFY\":null,\"POS_ITEM_RESTRICT_CODE\":null,\"PRICE_REQUIRED\":null,\"PRODUCT_GRADE\":\"000\",\"QUANTITY_REQUIRED\":null,\"SIGNS_LABELS\":\"10\",\"VISUAL_VERIFY\":null,\"A_48_HOUR_PRODUCT\":null,\"PRORATION_QTY_LIMIT\":0,\"PROFIT_CENTER\":\"0630-001\",\"PROFIT_CENTER_DESCR_EN\":\"Sydney Riv Meat\",\"PROFIT_CENTER_DESCR_FR\":null,\"FORECAST_PROFILE\":null,\"FORECAST_MODEL\":null,\"REFERENCEARTICLECONSUMPTIONDT\":\"0000-00-00\",\"REFARTCONSUMPTIONMULTIPLIER\":0.00,\"REFERENCEARTICLEFORCONSUMPTION\":null,\"DISCOUNT_FLAG\":\"Y\",\"ASSORTMENT\":\"0000000630\",\"VALID_TO_DATE\":\"9999-12-31\",\"VALID_FROM_DATE\":\"2012-04-26\",\"POSDEPARTMENTNUMBER\":\"001\",\"MINIMUMSHELFLIFE\":\"000000\",\"MAXIMUMSHELFLIFE\":\"000000\",\"MINIMUNACCEPTED\":\"000000\",\"CUSTOMERSHELFLIFE\":\"000000\",\"OSPRETAILERREGIONID\":\"ISF_NS03\",\"LOCATIONID\":\"11574\",\"SapInstorelocations\":[{\"UPC\":\"11904\",\"UNITOFMEASURE\":\"KG\",\"AISLE\":\"70\",\"AISLETYPE\":\"A\",\"SIDE\":\"L\",\"AISLESECTION\":\"00\",\"SHELF\":null,\"HASSALES\":null},{\"UPC\":\"21190400000\",\"UNITOFMEASURE\":\"KG\",\"AISLE\":\"70\",\"AISLETYPE\":\"A\",\"SIDE\":\"L\",\"AISLESECTION\":\"00\",\"SHELF\":null,\"HASSALES\":\"X\"}],\"PRIMARYVENDOR\":\"0000213623\",\"LOTSIZE\":null,\"ROUNDINGVALUE\":0.000,\"SITE_STATUS\":null},{\"SALES_ORGANIZATION\":\"3000\",\"REGION\":\"NS\",\"SITE_NUMBER\":\"0644\",\"SITENAME\":\"Sobeys Clayton Park\",\"SALESORGANIZATION\":\"3000\",\"PURCHASINGORGANIZATION\":\"3000\",\"DISTRIBUTIONCHANNEL\":\"48\",\"PURCHASING_GROUP\":\"002\",\"UNIT_OF_ISSUE\":\"KG\",\"ARTICLE_RP_PROFILE\":null,\"RP_TYPE\":\"ND\",\"STOCK_PLANNER_ARTICLES_PLANNER\":\"001\",\"PLANNED_DELIVERY_TIME_IN_DAYS\":0,\"PERIOD_INDICATOR\":\"T\",\"REORDER_POINT\":0.000,\"SAFETY_STOCK\":0.000,\"MAXIMUM_STOCK_LEVEL\":0.000,\"MAXIMUM_STORAGE_PERIOD\":5,\"MAXIMUM_STORAGE_PERIOD_UNIT\":\"10\",\"LOADING_GROUP\":\"0002\",\"QUOTA_ARRANGEMENT_USAGE\":null,\"GROUP_FOR_AVAILABILITY_CHECK\":\"KP\",\"SOURCE_OF_SUPPLY\":\"3\",\"COUNTRY_OF_ORIGIN\":null,\"PPC_PLANNING_CALENDAR\":null,\"PLANNING_CYCLE\":null,\"DEFAULT_STORAGE_LOCATION\":\"0001\",\"UNIT_OF_MEASURE_GROUP\":null,\"HANDLING_GROUP_WORKLOAD_CALC\":null,\"EXCLUDED_FROM_MINIMUM\":null,\"LABEL_QUANTITY\":\"01\",\"POS_AGE_VERIFY\":null,\"POS_ITEM_RESTRICT_CODE\":null,\"PRICE_REQUIRED\":null,\"PRODUCT_GRADE\":\"000\",\"QUANTITY_REQUIRED\":null,\"SIGNS_LABELS\":\"10\",\"VISUAL_VERIFY\":null,\"A_48_HOUR_PRODUCT\":null,\"PRORATION_QTY_LIMIT\":0,\"PROFIT_CENTER\":\"0644-001\",\"PROFIT_CENTER_DESCR_EN\":\"Clayton Pk Meat\",\"PROFIT_CENTER_DESCR_FR\":null,\"FORECAST_PROFILE\":null,\"FORECAST_MODEL\":null,\"REFERENCEARTICLECONSUMPTIONDT\":\"0000-00-00\",\"REFARTCONSUMPTIONMULTIPLIER\":0.00,\"REFERENCEARTICLEFORCONSUMPTION\":null,\"DISCOUNT_FLAG\":\"Y\",\"ASSORTMENT\":\"0000000644\",\"VALID_TO_DATE\":\"9999-12-31\",\"VALID_FROM_DATE\":\"2012-04-26\",\"POSDEPARTMENTNUMBER\":\"001\",\"MINIMUMSHELFLIFE\":\"000000\",\"MAXIMUMSHELFLIFE\":\"000000\",\"MINIMUNACCEPTED\":\"000000\",\"CUSTOMERSHELFLIFE\":\"000000\",\"OSPRETAILERREGIONID\":\"ISF_NS01\",\"LOCATIONID\":\"11529\",\"SapInstorelocations\":[{\"UPC\":\"11904\",\"UNITOFMEASURE\":\"KG\",\"AISLE\":\"29\",\"AISLETYPE\":\"A\",\"SIDE\":null,\"AISLESECTION\":\"00\",\"SHELF\":null,\"HASSALES\":null},{\"UPC\":\"21190400000\",\"UNITOFMEASURE\":\"KG\",\"AISLE\":\"29\",\"AISLETYPE\":\"A\",\"SIDE\":null,\"AISLESECTION\":\"00\",\"SHELF\":null,\"HASSALES\":null}],\"PRIMARYVENDOR\":\"0000213623\",\"LOTSIZE\":null,\"ROUNDINGVALUE\":0.000,\"SITE_STATUS\":null},{\"SALES_ORGANIZATION\":\"3000\",\"REGION\":\"NS\",\"SITE_NUMBER\":\"0670\",\"SITENAME\":\"Sobeys Lower Sackville\",\"SALESORGANIZATION\":\"3000\",\"PURCHASINGORGANIZATION\":\"3000\",\"DISTRIBUTIONCHANNEL\":\"48\",\"PURCHASING_GROUP\":\"002\",\"UNIT_OF_ISSUE\":\"KG\",\"ARTICLE_RP_PROFILE\":null,\"RP_TYPE\":\"ND\",\"STOCK_PLANNER_ARTICLES_PLANNER\":\"001\",\"PLANNED_DELIVERY_TIME_IN_DAYS\":0,\"PERIOD_INDICATOR\":\"T\",\"REORDER_POINT\":0.000,\"SAFETY_STOCK\":0.000,\"MAXIMUM_STOCK_LEVEL\":0.000,\"MAXIMUM_STORAGE_PERIOD\":5,\"MAXIMUM_STORAGE_PERIOD_UNIT\":\"10\",\"LOADING_GROUP\":\"0002\",\"QUOTA_ARRANGEMENT_USAGE\":null,\"GROUP_FOR_AVAILABILITY_CHECK\":\"KP\",\"SOURCE_OF_SUPPLY\":\"3\",\"COUNTRY_OF_ORIGIN\":null,\"PPC_PLANNING_CALENDAR\":null,\"PLANNING_CYCLE\":null,\"DEFAULT_STORAGE_LOCATION\":\"0001\",\"UNIT_OF_MEASURE_GROUP\":null,\"HANDLING_GROUP_WORKLOAD_CALC\":null,\"EXCLUDED_FROM_MINIMUM\":null,\"LABEL_QUANTITY\":\"01\",\"POS_AGE_VERIFY\":null,\"POS_ITEM_RESTRICT_CODE\":null,\"PRICE_REQUIRED\":null,\"PRODUCT_GRADE\":\"000\",\"QUANTITY_REQUIRED\":null,\"SIGNS_LABELS\":\"10\",\"VISUAL_VERIFY\":null,\"A_48_HOUR_PRODUCT\":null,\"PRORATION_QTY_LIMIT\":0,\"PROFIT_CENTER\":\"0670-001\",\"PROFIT_CENTER_DESCR_EN\":\"Lwr Sackvl Meat\",\"PROFIT_CENTER_DESCR_FR\":null,\"FORECAST_PROFILE\":null,\"FORECAST_MODEL\":null,\"REFERENCEARTICLECONSUMPTIONDT\":\"0000-00-00\",\"REFARTCONSUMPTIONMULTIPLIER\":0.00,\"REFERENCEARTICLEFORCONSUMPTION\":null,\"DISCOUNT_FLAG\":\"Y\",\"ASSORTMENT\":\"0000000670\",\"VALID_TO_DATE\":\"9999-12-31\",\"VALID_FROM_DATE\":\"2012-04-26\",\"POSDEPARTMENTNUMBER\":\"001\",\"MINIMUMSHELFLIFE\":\"000000\",\"MAXIMUMSHELFLIFE\":\"000000\",\"MINIMUNACCEPTED\":\"000000\",\"CUSTOMERSHELFLIFE\":\"000000\",\"OSPRETAILERREGIONID\":\"ISF_NS01\",\"LOCATIONID\":\"11534\",\"SapInstorelocations\":[{\"UPC\":\"11904\",\"UNITOFMEASURE\":\"KG\",\"AISLE\":\"60\",\"AISLETYPE\":\"A\",\"SIDE\":null,\"AISLESECTION\":\"00\",\"SHELF\":null,\"HASSALES\":null},{\"UPC\":\"21190400000\",\"UNITOFMEASURE\":\"KG\",\"AISLE\":\"60\",\"AISLETYPE\":\"A\",\"SIDE\":null,\"AISLESECTION\":\"00\",\"SHELF\":null,\"HASSALES\":\"X\"}],\"PRIMARYVENDOR\":\"0000213623\",\"LOTSIZE\":null,\"ROUNDINGVALUE\":0.000,\"SITE_STATUS\":null},{\"SALES_ORGANIZATION\":\"3000\",\"REGION\":\"NS\",\"SITE_NUMBER\":\"0684\",\"SITENAME\":\"Sobeys Tantallon\",\"SALESORGANIZATION\":\"3000\",\"PURCHASINGORGANIZATION\":\"3000\",\"DISTRIBUTIONCHANNEL\":\"48\",\"PURCHASING_GROUP\":\"002\",\"UNIT_OF_ISSUE\":\"KG\",\"ARTICLE_RP_PROFILE\":null,\"RP_TYPE\":\"ND\",\"STOCK_PLANNER_ARTICLES_PLANNER\":\"001\",\"PLANNED_DELIVERY_TIME_IN_DAYS\":0,\"PERIOD_INDICATOR\":\"T\",\"REORDER_POINT\":0.000,\"SAFETY_STOCK\":0.000,\"MAXIMUM_STOCK_LEVEL\":0.000,\"MAXIMUM_STORAGE_PERIOD\":5,\"MAXIMUM_STORAGE_PERIOD_UNIT\":\"10\",\"LOADING_GROUP\":\"0002\",\"QUOTA_ARRANGEMENT_USAGE\":null,\"GROUP_FOR_AVAILABILITY_CHECK\":\"KP\",\"SOURCE_OF_SUPPLY\":\"3\",\"COUNTRY_OF_ORIGIN\":null,\"PPC_PLANNING_CALENDAR\":null,\"PLANNING_CYCLE\":null,\"DEFAULT_STORAGE_LOCATION\":\"0001\",\"UNIT_OF_MEASURE_GROUP\":null,\"HANDLING_GROUP_WORKLOAD_CALC\":null,\"EXCLUDED_FROM_MINIMUM\":null,\"LABEL_QUANTITY\":\"01\",\"POS_AGE_VERIFY\":null,\"POS_ITEM_RESTRICT_CODE\":null,\"PRICE_REQUIRED\":null,\"PRODUCT_GRADE\":\"000\",\"QUANTITY_REQUIRED\":null,\"SIGNS_LABELS\":\"10\",\"VISUAL_VERIFY\":null,\"A_48_HOUR_PRODUCT\":null,\"PRORATION_QTY_LIMIT\":0,\"PROFIT_CENTER\":\"0684-001\",\"PROFIT_CENTER_DESCR_EN\":\"Tantallon Meat\",\"PROFIT_CENTER_DESCR_FR\":null,\"FORECAST_PROFILE\":null,\"FORECAST_MODEL\":null,\"REFERENCEARTICLECONSUMPTIONDT\":\"0000-00-00\",\"REFARTCONSUMPTIONMULTIPLIER\":0.00,\"REFERENCEARTICLEFORCONSUMPTION\":null,\"DISCOUNT_FLAG\":\"Y\",\"ASSORTMENT\":\"0000000684\",\"VALID_TO_DATE\":\"9999-12-31\",\"VALID_FROM_DATE\":\"2012-04-26\",\"POSDEPARTMENTNUMBER\":\"001\",\"MINIMUMSHELFLIFE\":\"000000\",\"MAXIMUMSHELFLIFE\":\"000000\",\"MINIMUNACCEPTED\":\"000000\",\"CUSTOMERSHELFLIFE\":\"000000\",\"OSPRETAILERREGIONID\":\"ISF_NS01\",\"LOCATIONID\":\"11578\",\"SapInstorelocations\":[{\"UPC\":\"11904\",\"UNITOFMEASURE\":\"KG\",\"AISLE\":\"00\",\"AISLETYPE\":null,\"SIDE\":null,\"AISLESECTION\":\"00\",\"SHELF\":null,\"HASSALES\":null},{\"UPC\":\"21190400000\",\"UNITOFMEASURE\":\"KG\",\"AISLE\":\"00\",\"AISLETYPE\":null,\"SIDE\":null,\"AISLESECTION\":\"00\",\"SHELF\":null,\"HASSALES\":\"X\"}],\"PRIMARYVENDOR\":\"0000213623\",\"LOTSIZE\":null,\"ROUNDINGVALUE\":0.000,\"SITE_STATUS\":null},{\"SALES_ORGANIZATION\":\"3000\",\"REGION\":\"NS\",\"SITE_NUMBER\":\"0725\",\"SITENAME\":\"Sobeys Bedford South\",\"SALESORGANIZATION\":\"3000\",\"PURCHASINGORGANIZATION\":\"3000\",\"DISTRIBUTIONCHANNEL\":\"48\",\"PURCHASING_GROUP\":\"002\",\"UNIT_OF_ISSUE\":\"KG\",\"ARTICLE_RP_PROFILE\":null,\"RP_TYPE\":\"ND\",\"STOCK_PLANNER_ARTICLES_PLANNER\":\"001\",\"PLANNED_DELIVERY_TIME_IN_DAYS\":0,\"PERIOD_INDICATOR\":\"T\",\"REORDER_POINT\":0.000,\"SAFETY_STOCK\":0.000,\"MAXIMUM_STOCK_LEVEL\":0.000,\"MAXIMUM_STORAGE_PERIOD\":5,\"MAXIMUM_STORAGE_PERIOD_UNIT\":\"10\",\"LOADING_GROUP\":\"0002\",\"QUOTA_ARRANGEMENT_USAGE\":null,\"GROUP_FOR_AVAILABILITY_CHECK\":\"KP\",\"SOURCE_OF_SUPPLY\":\"3\",\"COUNTRY_OF_ORIGIN\":null,\"PPC_PLANNING_CALENDAR\":null,\"PLANNING_CYCLE\":null,\"DEFAULT_STORAGE_LOCATION\":\"0001\",\"UNIT_OF_MEASURE_GROUP\":null,\"HANDLING_GROUP_WORKLOAD_CALC\":null,\"EXCLUDED_FROM_MINIMUM\":null,\"LABEL_QUANTITY\":\"01\",\"POS_AGE_VERIFY\":null,\"POS_ITEM_RESTRICT_CODE\":null,\"PRICE_REQUIRED\":null,\"PRODUCT_GRADE\":\"000\",\"QUANTITY_REQUIRED\":null,\"SIGNS_LABELS\":\"10\",\"VISUAL_VERIFY\":null,\"A_48_HOUR_PRODUCT\":null,\"PRORATION_QTY_LIMIT\":0,\"PROFIT_CENTER\":\"0725-001\",\"PROFIT_CENTER_DESCR_EN\":\"Bedford South Meat\",\"PROFIT_CENTER_DESCR_FR\":null,\"FORECAST_PROFILE\":null,\"FORECAST_MODEL\":null,\"REFERENCEARTICLECONSUMPTIONDT\":\"0000-00-00\",\"REFARTCONSUMPTIONMULTIPLIER\":0.00,\"REFERENCEARTICLEFORCONSUMPTION\":null,\"DISCOUNT_FLAG\":\"Y\",\"ASSORTMENT\":\"0000000725\",\"VALID_TO_DATE\":\"9999-12-31\",\"VALID_FROM_DATE\":\"2012-04-26\",\"POSDEPARTMENTNUMBER\":\"001\",\"MINIMUMSHELFLIFE\":\"000000\",\"MAXIMUMSHELFLIFE\":\"000000\",\"MINIMUNACCEPTED\":\"000000\",\"CUSTOMERSHELFLIFE\":\"000000\",\"OSPRETAILERREGIONID\":\"ISF_NS01\",\"LOCATIONID\":\"17606\",\"SapInstorelocations\":[{\"UPC\":\"11904\",\"UNITOFMEASURE\":\"KG\",\"AISLE\":\"60\",\"AISLETYPE\":\"A\",\"SIDE\":null,\"AISLESECTION\":\"00\",\"SHELF\":null,\"HASSALES\":null},{\"UPC\":\"21190400000\",\"UNITOFMEASURE\":\"KG\",\"AISLE\":\"60\",\"AISLETYPE\":\"A\",\"SIDE\":null,\"AISLESECTION\":\"00\",\"SHELF\":null,\"HASSALES\":\"X\"}],\"PRIMARYVENDOR\":\"0000213623\",\"LOTSIZE\":null,\"ROUNDINGVALUE\":0.000,\"SITE_STATUS\":null},{\"SALES_ORGANIZATION\":\"3000\",\"REGION\":\"NL\",\"SITE_NUMBER\":\"0744\",\"SITENAME\":\"Sobeys St John's Howley Estate\",\"SALESORGANIZATION\":\"3000\",\"PURCHASINGORGANIZATION\":\"3000\",\"DISTRIBUTIONCHANNEL\":\"49\",\"PURCHASING_GROUP\":\"002\",\"UNIT_OF_ISSUE\":\"KG\",\"ARTICLE_RP_PROFILE\":null,\"RP_TYPE\":\"ND\",\"STOCK_PLANNER_ARTICLES_PLANNER\":\"001\",\"PLANNED_DELIVERY_TIME_IN_DAYS\":0,\"PERIOD_INDICATOR\":\"T\",\"REORDER_POINT\":0.000,\"SAFETY_STOCK\":0.000,\"MAXIMUM_STOCK_LEVEL\":0.000,\"MAXIMUM_STORAGE_PERIOD\":5,\"MAXIMUM_STORAGE_PERIOD_UNIT\":\"10\",\"LOADING_GROUP\":\"0002\",\"QUOTA_ARRANGEMENT_USAGE\":null,\"GROUP_FOR_AVAILABILITY_CHECK\":\"KP\",\"SOURCE_OF_SUPPLY\":\"3\",\"COUNTRY_OF_ORIGIN\":null,\"PPC_PLANNING_CALENDAR\":null,\"PLANNING_CYCLE\":null,\"DEFAULT_STORAGE_LOCATION\":\"0001\",\"UNIT_OF_MEASURE_GROUP\":null,\"HANDLING_GROUP_WORKLOAD_CALC\":null,\"EXCLUDED_FROM_MINIMUM\":null,\"LABEL_QUANTITY\":\"01\",\"POS_AGE_VERIFY\":null,\"POS_ITEM_RESTRICT_CODE\":null,\"PRICE_REQUIRED\":null,\"PRODUCT_GRADE\":\"000\",\"QUANTITY_REQUIRED\":null,\"SIGNS_LABELS\":\"10\",\"VISUAL_VERIFY\":null,\"A_48_HOUR_PRODUCT\":null,\"PRORATION_QTY_LIMIT\":0,\"PROFIT_CENTER\":\"0744-001\",\"PROFIT_CENTER_DESCR_EN\":\"Howley Estate Meat\",\"PROFIT_CENTER_DESCR_FR\":null,\"FORECAST_PROFILE\":null,\"FORECAST_MODEL\":null,\"REFERENCEARTICLECONSUMPTIONDT\":\"0000-00-00\",\"REFARTCONSUMPTIONMULTIPLIER\":0.00,\"REFERENCEARTICLEFORCONSUMPTION\":null,\"DISCOUNT_FLAG\":\"Y\",\"ASSORTMENT\":\"0000000744\",\"VALID_TO_DATE\":\"9999-12-31\",\"VALID_FROM_DATE\":\"2012-04-26\",\"POSDEPARTMENTNUMBER\":\"001\",\"MINIMUMSHELFLIFE\":\"000000\",\"MAXIMUMSHELFLIFE\":\"000000\",\"MINIMUNACCEPTED\":\"000000\",\"CUSTOMERSHELFLIFE\":\"000000\",\"OSPRETAILERREGIONID\":\"ISF_NL01\",\"LOCATIONID\":\"11561\",\"SapInstorelocations\":[{\"UPC\":\"11904\",\"UNITOFMEASURE\":\"KG\",\"AISLE\":\"70\",\"AISLETYPE\":\"A\",\"SIDE\":\"L\",\"AISLESECTION\":\"00\",\"SHELF\":null,\"HASSALES\":null},{\"UPC\":\"21190400000\",\"UNITOFMEASURE\":\"KG\",\"AISLE\":\"70\",\"AISLETYPE\":\"A\",\"SIDE\":\"L\",\"AISLESECTION\":\"00\",\"SHELF\":null,\"HASSALES\":\"X\"}],\"PRIMARYVENDOR\":\"0000213623\",\"LOTSIZE\":null,\"ROUNDINGVALUE\":0.000,\"SITE_STATUS\":null},{\"SALES_ORGANIZATION\":\"3000\",\"REGION\":\"NS\",\"SITE_NUMBER\":\"0758\",\"SITENAME\":\"Sobeys Russell Lake\",\"SALESORGANIZATION\":\"3000\",\"PURCHASINGORGANIZATION\":\"3000\",\"DISTRIBUTIONCHANNEL\":\"48\",\"PURCHASING_GROUP\":\"002\",\"UNIT_OF_ISSUE\":\"KG\",\"ARTICLE_RP_PROFILE\":null,\"RP_TYPE\":\"ND\",\"STOCK_PLANNER_ARTICLES_PLANNER\":\"001\",\"PLANNED_DELIVERY_TIME_IN_DAYS\":0,\"PERIOD_INDICATOR\":\"T\",\"REORDER_POINT\":0.000,\"SAFETY_STOCK\":0.000,\"MAXIMUM_STOCK_LEVEL\":0.000,\"MAXIMUM_STORAGE_PERIOD\":5,\"MAXIMUM_STORAGE_PERIOD_UNIT\":\"10\",\"LOADING_GROUP\":\"0002\",\"QUOTA_ARRANGEMENT_USAGE\":null,\"GROUP_FOR_AVAILABILITY_CHECK\":\"KP\",\"SOURCE_OF_SUPPLY\":\"3\",\"COUNTRY_OF_ORIGIN\":null,\"PPC_PLANNING_CALENDAR\":null,\"PLANNING_CYCLE\":null,\"DEFAULT_STORAGE_LOCATION\":\"0001\",\"UNIT_OF_MEASURE_GROUP\":null,\"HANDLING_GROUP_WORKLOAD_CALC\":null,\"EXCLUDED_FROM_MINIMUM\":null,\"LABEL_QUANTITY\":\"01\",\"POS_AGE_VERIFY\":null,\"POS_ITEM_RESTRICT_CODE\":null,\"PRICE_REQUIRED\":null,\"PRODUCT_GRADE\":\"000\",\"QUANTITY_REQUIRED\":null,\"SIGNS_LABELS\":\"10\",\"VISUAL_VERIFY\":null,\"A_48_HOUR_PRODUCT\":null,\"PRORATION_QTY_LIMIT\":0,\"PROFIT_CENTER\":\"0758-001\",\"PROFIT_CENTER_DESCR_EN\":\"Russell Lake Meat\",\"PROFIT_CENTER_DESCR_FR\":null,\"FORECAST_PROFILE\":null,\"FORECAST_MODEL\":null,\"REFERENCEARTICLECONSUMPTIONDT\":\"0000-00-00\",\"REFARTCONSUMPTIONMULTIPLIER\":0.00,\"REFERENCEARTICLEFORCONSUMPTION\":null,\"DISCOUNT_FLAG\":\"Y\",\"ASSORTMENT\":\"0000000758\",\"VALID_TO_DATE\":\"9999-12-31\",\"VALID_FROM_DATE\":\"2012-04-26\",\"POSDEPARTMENTNUMBER\":\"001\",\"MINIMUMSHELFLIFE\":\"000000\",\"MAXIMUMSHELFLIFE\":\"000000\",\"MINIMUNACCEPTED\":\"000000\",\"CUSTOMERSHELFLIFE\":\"000000\",\"OSPRETAILERREGIONID\":\"ISF_NS01\",\"LOCATIONID\":\"15824\",\"SapInstorelocations\":[{\"UPC\":\"11904\",\"UNITOFMEASURE\":\"KG\",\"AISLE\":\"00\",\"AISLETYPE\":null,\"SIDE\":null,\"AISLESECTION\":\"00\",\"SHELF\":null,\"HASSALES\":null},{\"UPC\":\"21190400000\",\"UNITOFMEASURE\":\"KG\",\"AISLE\":\"00\",\"AISLETYPE\":null,\"SIDE\":null,\"AISLESECTION\":\"00\",\"SHELF\":null,\"HASSALES\":\"X\"}],\"PRIMARYVENDOR\":\"0000213623\",\"LOTSIZE\":null,\"ROUNDINGVALUE\":0.000,\"SITE_STATUS\":null},{\"SALES_ORGANIZATION\":\"3000\",\"REGION\":\"NS\",\"SITE_NUMBER\":\"0772\",\"SITENAME\":\"Sobeys Tacoma Drive\",\"SALESORGANIZATION\":\"3000\",\"PURCHASINGORGANIZATION\":\"3000\",\"DISTRIBUTIONCHANNEL\":\"48\",\"PURCHASING_GROUP\":\"002\",\"UNIT_OF_ISSUE\":\"KG\",\"ARTICLE_RP_PROFILE\":null,\"RP_TYPE\":\"ND\",\"STOCK_PLANNER_ARTICLES_PLANNER\":\"001\",\"PLANNED_DELIVERY_TIME_IN_DAYS\":0,\"PERIOD_INDICATOR\":\"T\",\"REORDER_POINT\":0.000,\"SAFETY_STOCK\":0.000,\"MAXIMUM_STOCK_LEVEL\":0.000,\"MAXIMUM_STORAGE_PERIOD\":5,\"MAXIMUM_STORAGE_PERIOD_UNIT\":\"10\",\"LOADING_GROUP\":\"0002\",\"QUOTA_ARRANGEMENT_USAGE\":null,\"GROUP_FOR_AVAILABILITY_CHECK\":\"KP\",\"SOURCE_OF_SUPPLY\":\"3\",\"COUNTRY_OF_ORIGIN\":null,\"PPC_PLANNING_CALENDAR\":null,\"PLANNING_CYCLE\":null,\"DEFAULT_STORAGE_LOCATION\":\"0001\",\"UNIT_OF_MEASURE_GROUP\":null,\"HANDLING_GROUP_WORKLOAD_CALC\":null,\"EXCLUDED_FROM_MINIMUM\":null,\"LABEL_QUANTITY\":\"01\",\"POS_AGE_VERIFY\":null,\"POS_ITEM_RESTRICT_CODE\":null,\"PRICE_REQUIRED\":null,\"PRODUCT_GRADE\":\"000\",\"QUANTITY_REQUIRED\":null,\"SIGNS_LABELS\":\"10\",\"VISUAL_VERIFY\":null,\"A_48_HOUR_PRODUCT\":null,\"PRORATION_QTY_LIMIT\":0,\"PROFIT_CENTER\":\"0772-001\",\"PROFIT_CENTER_DESCR_EN\":\"Tacoma Dr Meat\",\"PROFIT_CENTER_DESCR_FR\":null,\"FORECAST_PROFILE\":null,\"FORECAST_MODEL\":null,\"REFERENCEARTICLECONSUMPTIONDT\":\"0000-00-00\",\"REFARTCONSUMPTIONMULTIPLIER\":0.00,\"REFERENCEARTICLEFORCONSUMPTION\":null,\"DISCOUNT_FLAG\":\"Y\",\"ASSORTMENT\":\"0000000772\",\"VALID_TO_DATE\":\"9999-12-31\",\"VALID_FROM_DATE\":\"2012-04-26\",\"POSDEPARTMENTNUMBER\":\"001\",\"MINIMUMSHELFLIFE\":\"000000\",\"MAXIMUMSHELFLIFE\":\"000000\",\"MINIMUNACCEPTED\":\"000000\",\"CUSTOMERSHELFLIFE\":\"000000\",\"OSPRETAILERREGIONID\":\"ISF_NS01\",\"LOCATIONID\":\"16164\",\"SapInstorelocations\":[{\"UPC\":\"11904\",\"UNITOFMEASURE\":\"KG\",\"AISLE\":\"00\",\"AISLETYPE\":null,\"SIDE\":null,\"AISLESECTION\":\"00\",\"SHELF\":null,\"HASSALES\":null},{\"UPC\":\"21190400000\",\"UNITOFMEASURE\":\"KG\",\"AISLE\":\"00\",\"AISLETYPE\":null,\"SIDE\":null,\"AISLESECTION\":\"00\",\"SHELF\":null,\"HASSALES\":\"X\"}],\"PRIMARYVENDOR\":\"0000213623\",\"LOTSIZE\":null,\"ROUNDINGVALUE\":0.000,\"SITE_STATUS\":null},{\"SALES_ORGANIZATION\":\"3000\",\"REGION\":\"NS\",\"SITE_NUMBER\":\"0776\",\"SITENAME\":\"Sobeys Penhorn\",\"SALESORGANIZATION\":\"3000\",\"PURCHASINGORGANIZATION\":\"3000\",\"DISTRIBUTIONCHANNEL\":\"48\",\"PURCHASING_GROUP\":\"002\",\"UNIT_OF_ISSUE\":\"KG\",\"ARTICLE_RP_PROFILE\":null,\"RP_TYPE\":\"ND\",\"STOCK_PLANNER_ARTICLES_PLANNER\":\"001\",\"PLANNED_DELIVERY_TIME_IN_DAYS\":0,\"PERIOD_INDICATOR\":\"T\",\"REORDER_POINT\":0.000,\"SAFETY_STOCK\":0.000,\"MAXIMUM_STOCK_LEVEL\":0.000,\"MAXIMUM_STORAGE_PERIOD\":5,\"MAXIMUM_STORAGE_PERIOD_UNIT\":\"10\",\"LOADING_GROUP\":\"0002\",\"QUOTA_ARRANGEMENT_USAGE\":null,\"GROUP_FOR_AVAILABILITY_CHECK\":\"KP\",\"SOURCE_OF_SUPPLY\":\"3\",\"COUNTRY_OF_ORIGIN\":null,\"PPC_PLANNING_CALENDAR\":null,\"PLANNING_CYCLE\":null,\"DEFAULT_STORAGE_LOCATION\":\"0001\",\"UNIT_OF_MEASURE_GROUP\":null,\"HANDLING_GROUP_WORKLOAD_CALC\":null,\"EXCLUDED_FROM_MINIMUM\":null,\"LABEL_QUANTITY\":\"01\",\"POS_AGE_VERIFY\":null,\"POS_ITEM_RESTRICT_CODE\":null,\"PRICE_REQUIRED\":null,\"PRODUCT_GRADE\":\"000\",\"QUANTITY_REQUIRED\":null,\"SIGNS_LABELS\":\"10\",\"VISUAL_VERIFY\":null,\"A_48_HOUR_PRODUCT\":null,\"PRORATION_QTY_LIMIT\":0,\"PROFIT_CENTER\":\"0776-001\",\"PROFIT_CENTER_DESCR_EN\":\"Penhorn Meat\",\"PROFIT_CENTER_DESCR_FR\":null,\"FORECAST_PROFILE\":null,\"FORECAST_MODEL\":null,\"REFERENCEARTICLECONSUMPTIONDT\":\"0000-00-00\",\"REFARTCONSUMPTIONMULTIPLIER\":0.00,\"REFERENCEARTICLEFORCONSUMPTION\":null,\"DISCOUNT_FLAG\":\"Y\",\"ASSORTMENT\":\"0000000776\",\"VALID_TO_DATE\":\"9999-12-31\",\"VALID_FROM_DATE\":\"2012-04-26\",\"POSDEPARTMENTNUMBER\":\"001\",\"MINIMUMSHELFLIFE\":\"000000\",\"MAXIMUMSHELFLIFE\":\"000000\",\"MINIMUNACCEPTED\":\"000000\",\"CUSTOMERSHELFLIFE\":\"000000\",\"OSPRETAILERREGIONID\":\"ISF_NS01\",\"LOCATIONID\":\"16344\",\"SapInstorelocations\":[{\"UPC\":\"11904\",\"UNITOFMEASURE\":\"KG\",\"AISLE\":\"12\",\"AISLETYPE\":\"A\",\"SIDE\":null,\"AISLESECTION\":\"00\",\"SHELF\":null,\"HASSALES\":null},{\"UPC\":\"21190400000\",\"UNITOFMEASURE\":\"KG\",\"AISLE\":\"12\",\"AISLETYPE\":\"A\",\"SIDE\":null,\"AISLESECTION\":\"00\",\"SHELF\":null,\"HASSALES\":\"X\"}],\"PRIMARYVENDOR\":\"0000213623\",\"LOTSIZE\":null,\"ROUNDINGVALUE\":0.000,\"SITE_STATUS\":null},{\"SALES_ORGANIZATION\":\"3000\",\"REGION\":\"NB\",\"SITE_NUMBER\":\"0778\",\"SITENAME\":\"Sobeys Saint John West\",\"SALESORGANIZATION\":\"3000\",\"PURCHASINGORGANIZATION\":\"3000\",\"DISTRIBUTIONCHANNEL\":\"48\",\"PURCHASING_GROUP\":\"002\",\"UNIT_OF_ISSUE\":\"KG\",\"ARTICLE_RP_PROFILE\":null,\"RP_TYPE\":\"ND\",\"STOCK_PLANNER_ARTICLES_PLANNER\":\"001\",\"PLANNED_DELIVERY_TIME_IN_DAYS\":0,\"PERIOD_INDICATOR\":\"T\",\"REORDER_POINT\":0.000,\"SAFETY_STOCK\":0.000,\"MAXIMUM_STOCK_LEVEL\":0.000,\"MAXIMUM_STORAGE_PERIOD\":5,\"MAXIMUM_STORAGE_PERIOD_UNIT\":\"10\",\"LOADING_GROUP\":\"0002\",\"QUOTA_ARRANGEMENT_USAGE\":null,\"GROUP_FOR_AVAILABILITY_CHECK\":\"KP\",\"SOURCE_OF_SUPPLY\":\"3\",\"COUNTRY_OF_ORIGIN\":null,\"PPC_PLANNING_CALENDAR\":null,\"PLANNING_CYCLE\":null,\"DEFAULT_STORAGE_LOCATION\":\"0001\",\"UNIT_OF_MEASURE_GROUP\":null,\"HANDLING_GROUP_WORKLOAD_CALC\":null,\"EXCLUDED_FROM_MINIMUM\":null,\"LABEL_QUANTITY\":\"01\",\"POS_AGE_VERIFY\":null,\"POS_ITEM_RESTRICT_CODE\":null,\"PRICE_REQUIRED\":null,\"PRODUCT_GRADE\":\"000\",\"QUANTITY_REQUIRED\":null,\"SIGNS_LABELS\":\"10\",\"VISUAL_VERIFY\":null,\"A_48_HOUR_PRODUCT\":null,\"PRORATION_QTY_LIMIT\":0,\"PROFIT_CENTER\":\"0778-001\",\"PROFIT_CENTER_DESCR_EN\":\"Saint John West Meat\",\"PROFIT_CENTER_DESCR_FR\":null,\"FORECAST_PROFILE\":null,\"FORECAST_MODEL\":null,\"REFERENCEARTICLECONSUMPTIONDT\":\"0000-00-00\",\"REFARTCONSUMPTIONMULTIPLIER\":0.00,\"REFERENCEARTICLEFORCONSUMPTION\":null,\"DISCOUNT_FLAG\":\"Y\",\"ASSORTMENT\":\"0000000778\",\"VALID_TO_DATE\":\"9999-12-31\",\"VALID_FROM_DATE\":\"2012-04-26\",\"POSDEPARTMENTNUMBER\":\"001\",\"MINIMUMSHELFLIFE\":\"000000\",\"MAXIMUMSHELFLIFE\":\"000000\",\"MINIMUNACCEPTED\":\"000000\",\"CUSTOMERSHELFLIFE\":\"000000\",\"OSPRETAILERREGIONID\":\"ISF_NB01\",\"LOCATIONID\":\"16224\",\"SapInstorelocations\":[{\"UPC\":\"11904\",\"UNITOFMEASURE\":\"KG\",\"AISLE\":\"00\",\"AISLETYPE\":null,\"SIDE\":null,\"AISLESECTION\":\"00\",\"SHELF\":null,\"HASSALES\":null},{\"UPC\":\"21190400000\",\"UNITOFMEASURE\":\"KG\",\"AISLE\":\"00\",\"AISLETYPE\":null,\"SIDE\":null,\"AISLESECTION\":\"00\",\"SHELF\":null,\"HASSALES\":\"X\"}],\"PRIMARYVENDOR\":\"0000213623\",\"LOTSIZE\":null,\"ROUNDINGVALUE\":0.000,\"SITE_STATUS\":null},{\"SALES_ORGANIZATION\":\"3000\",\"REGION\":\"NS\",\"SITE_NUMBER\":\"0806\",\"SITENAME\":\"Sobeys Wyse Road\",\"SALESORGANIZATION\":\"3000\",\"PURCHASINGORGANIZATION\":\"3000\",\"DISTRIBUTIONCHANNEL\":\"48\",\"PURCHASING_GROUP\":\"002\",\"UNIT_OF_ISSUE\":\"KG\",\"ARTICLE_RP_PROFILE\":null,\"RP_TYPE\":\"ND\",\"STOCK_PLANNER_ARTICLES_PLANNER\":\"001\",\"PLANNED_DELIVERY_TIME_IN_DAYS\":0,\"PERIOD_INDICATOR\":\"T\",\"REORDER_POINT\":0.000,\"SAFETY_STOCK\":0.000,\"MAXIMUM_STOCK_LEVEL\":0.000,\"MAXIMUM_STORAGE_PERIOD\":5,\"MAXIMUM_STORAGE_PERIOD_UNIT\":\"10\",\"LOADING_GROUP\":\"0002\",\"QUOTA_ARRANGEMENT_USAGE\":null,\"GROUP_FOR_AVAILABILITY_CHECK\":\"KP\",\"SOURCE_OF_SUPPLY\":\"3\",\"COUNTRY_OF_ORIGIN\":null,\"PPC_PLANNING_CALENDAR\":null,\"PLANNING_CYCLE\":null,\"DEFAULT_STORAGE_LOCATION\":\"0001\",\"UNIT_OF_MEASURE_GROUP\":null,\"HANDLING_GROUP_WORKLOAD_CALC\":null,\"EXCLUDED_FROM_MINIMUM\":null,\"LABEL_QUANTITY\":\"01\",\"POS_AGE_VERIFY\":null,\"POS_ITEM_RESTRICT_CODE\":null,\"PRICE_REQUIRED\":null,\"PRODUCT_GRADE\":\"000\",\"QUANTITY_REQUIRED\":null,\"SIGNS_LABELS\":\"10\",\"VISUAL_VERIFY\":null,\"A_48_HOUR_PRODUCT\":null,\"PRORATION_QTY_LIMIT\":0,\"PROFIT_CENTER\":\"0806-001\",\"PROFIT_CENTER_DESCR_EN\":\"Wyse Road Meat\",\"PROFIT_CENTER_DESCR_FR\":null,\"FORECAST_PROFILE\":null,\"FORECAST_MODEL\":null,\"REFERENCEARTICLECONSUMPTIONDT\":\"0000-00-00\",\"REFARTCONSUMPTIONMULTIPLIER\":0.00,\"REFERENCEARTICLEFORCONSUMPTION\":null,\"DISCOUNT_FLAG\":\"Y\",\"ASSORTMENT\":\"0000000806\",\"VALID_TO_DATE\":\"9999-12-31\",\"VALID_FROM_DATE\":\"2013-01-21\",\"POSDEPARTMENTNUMBER\":\"001\",\"MINIMUMSHELFLIFE\":\"000000\",\"MAXIMUMSHELFLIFE\":\"000000\",\"MINIMUNACCEPTED\":\"000000\",\"CUSTOMERSHELFLIFE\":\"000000\",\"OSPRETAILERREGIONID\":\"ISF_NS01\",\"LOCATIONID\":\"19424\",\"SapInstorelocations\":[{\"UPC\":\"11904\",\"UNITOFMEASURE\":\"KG\",\"AISLE\":\"70\",\"AISLETYPE\":\"A\",\"SIDE\":null,\"AISLESECTION\":\"00\",\"SHELF\":null,\"HASSALES\":null},{\"UPC\":\"21190400000\",\"UNITOFMEASURE\":\"KG\",\"AISLE\":\"00\",\"AISLETYPE\":null,\"SIDE\":null,\"AISLESECTION\":\"00\",\"SHELF\":null,\"HASSALES\":\"X\"}],\"PRIMARYVENDOR\":\"0000213623\",\"LOTSIZE\":null,\"ROUNDINGVALUE\":0.000,\"SITE_STATUS\":null},{\"SALES_ORGANIZATION\":\"3000\",\"REGION\":\"NL\",\"SITE_NUMBER\":\"0855\",\"SITENAME\":\"Sobeys Mount Pearl\",\"SALESORGANIZATION\":\"3000\",\"PURCHASINGORGANIZATION\":\"3000\",\"DISTRIBUTIONCHANNEL\":\"49\",\"PURCHASING_GROUP\":\"002\",\"UNIT_OF_ISSUE\":\"KG\",\"ARTICLE_RP_PROFILE\":null,\"RP_TYPE\":\"ND\",\"STOCK_PLANNER_ARTICLES_PLANNER\":\"001\",\"PLANNED_DELIVERY_TIME_IN_DAYS\":0,\"PERIOD_INDICATOR\":\"T\",\"REORDER_POINT\":0.000,\"SAFETY_STOCK\":0.000,\"MAXIMUM_STOCK_LEVEL\":0.000,\"MAXIMUM_STORAGE_PERIOD\":5,\"MAXIMUM_STORAGE_PERIOD_UNIT\":\"10\",\"LOADING_GROUP\":\"0002\",\"QUOTA_ARRANGEMENT_USAGE\":null,\"GROUP_FOR_AVAILABILITY_CHECK\":\"KP\",\"SOURCE_OF_SUPPLY\":\"3\",\"COUNTRY_OF_ORIGIN\":null,\"PPC_PLANNING_CALENDAR\":null,\"PLANNING_CYCLE\":null,\"DEFAULT_STORAGE_LOCATION\":\"0001\",\"UNIT_OF_MEASURE_GROUP\":null,\"HANDLING_GROUP_WORKLOAD_CALC\":null,\"EXCLUDED_FROM_MINIMUM\":null,\"LABEL_QUANTITY\":\"01\",\"POS_AGE_VERIFY\":null,\"POS_ITEM_RESTRICT_CODE\":null,\"PRICE_REQUIRED\":null,\"PRODUCT_GRADE\":\"000\",\"QUANTITY_REQUIRED\":null,\"SIGNS_LABELS\":\"10\",\"VISUAL_VERIFY\":null,\"A_48_HOUR_PRODUCT\":null,\"PRORATION_QTY_LIMIT\":0,\"PROFIT_CENTER\":\"0855-001\",\"PROFIT_CENTER_DESCR_EN\":\"Mount Pearl Meat\",\"PROFIT_CENTER_DESCR_FR\":null,\"FORECAST_PROFILE\":null,\"FORECAST_MODEL\":null,\"REFERENCEARTICLECONSUMPTIONDT\":\"0000-00-00\",\"REFARTCONSUMPTIONMULTIPLIER\":0.00,\"REFERENCEARTICLEFORCONSUMPTION\":null,\"DISCOUNT_FLAG\":\"Y\",\"ASSORTMENT\":\"0000000855\",\"VALID_TO_DATE\":\"9999-12-31\",\"VALID_FROM_DATE\":\"2012-04-26\",\"POSDEPARTMENTNUMBER\":\"001\",\"MINIMUMSHELFLIFE\":\"000000\",\"MAXIMUMSHELFLIFE\":\"000000\",\"MINIMUNACCEPTED\":\"000000\",\"CUSTOMERSHELFLIFE\":\"000000\",\"OSPRETAILERREGIONID\":\"ISF_NL01\",\"LOCATIONID\":\"11542\",\"SapInstorelocations\":[{\"UPC\":\"11904\",\"UNITOFMEASURE\":\"KG\",\"AISLE\":\"99\",\"AISLETYPE\":\"A\",\"SIDE\":null,\"AISLESECTION\":\"00\",\"SHELF\":null,\"HASSALES\":null},{\"UPC\":\"21190400000\",\"UNITOFMEASURE\":\"KG\",\"AISLE\":\"99\",\"AISLETYPE\":\"A\",\"SIDE\":null,\"AISLESECTION\":\"00\",\"SHELF\":null,\"HASSALES\":\"X\"}],\"PRIMARYVENDOR\":\"0000213623\",\"LOTSIZE\":null,\"ROUNDINGVALUE\":0.000,\"SITE_STATUS\":null},{\"SALES_ORGANIZATION\":\"3000\",\"REGION\":\"NS\",\"SITE_NUMBER\":\"0881\",\"SITENAME\":\"Sobeys Mumford Road\",\"SALESORGANIZATION\":\"3000\",\"PURCHASINGORGANIZATION\":\"3000\",\"DISTRIBUTIONCHANNEL\":\"48\",\"PURCHASING_GROUP\":\"002\",\"UNIT_OF_ISSUE\":\"KG\",\"ARTICLE_RP_PROFILE\":null,\"RP_TYPE\":\"ND\",\"STOCK_PLANNER_ARTICLES_PLANNER\":\"001\",\"PLANNED_DELIVERY_TIME_IN_DAYS\":0,\"PERIOD_INDICATOR\":\"T\",\"REORDER_POINT\":0.000,\"SAFETY_STOCK\":0.000,\"MAXIMUM_STOCK_LEVEL\":0.000,\"MAXIMUM_STORAGE_PERIOD\":5,\"MAXIMUM_STORAGE_PERIOD_UNIT\":\"10\",\"LOADING_GROUP\":\"0002\",\"QUOTA_ARRANGEMENT_USAGE\":null,\"GROUP_FOR_AVAILABILITY_CHECK\":\"KP\",\"SOURCE_OF_SUPPLY\":\"3\",\"COUNTRY_OF_ORIGIN\":null,\"PPC_PLANNING_CALENDAR\":null,\"PLANNING_CYCLE\":null,\"DEFAULT_STORAGE_LOCATION\":\"0001\",\"UNIT_OF_MEASURE_GROUP\":null,\"HANDLING_GROUP_WORKLOAD_CALC\":null,\"EXCLUDED_FROM_MINIMUM\":null,\"LABEL_QUANTITY\":\"01\",\"POS_AGE_VERIFY\":null,\"POS_ITEM_RESTRICT_CODE\":null,\"PRICE_REQUIRED\":null,\"PRODUCT_GRADE\":\"000\",\"QUANTITY_REQUIRED\":null,\"SIGNS_LABELS\":\"10\",\"VISUAL_VERIFY\":null,\"A_48_HOUR_PRODUCT\":null,\"PRORATION_QTY_LIMIT\":0,\"PROFIT_CENTER\":\"0881-001\",\"PROFIT_CENTER_DESCR_EN\":\"West End Mall Meat\",\"PROFIT_CENTER_DESCR_FR\":null,\"FORECAST_PROFILE\":null,\"FORECAST_MODEL\":null,\"REFERENCEARTICLECONSUMPTIONDT\":\"0000-00-00\",\"REFARTCONSUMPTIONMULTIPLIER\":0.00,\"REFERENCEARTICLEFORCONSUMPTION\":null,\"DISCOUNT_FLAG\":\"Y\",\"ASSORTMENT\":\"0000000881\",\"VALID_TO_DATE\":\"9999-12-31\",\"VALID_FROM_DATE\":\"2012-04-26\",\"POSDEPARTMENTNUMBER\":\"001\",\"MINIMUMSHELFLIFE\":\"000000\",\"MAXIMUMSHELFLIFE\":\"000000\",\"MINIMUNACCEPTED\":\"000000\",\"CUSTOMERSHELFLIFE\":\"000000\",\"OSPRETAILERREGIONID\":\"ISF_NS01\",\"LOCATIONID\":\"11530\",\"SapInstorelocations\":[{\"UPC\":\"11904\",\"UNITOFMEASURE\":\"KG\",\"AISLE\":\"70\",\"AISLETYPE\":\"A\",\"SIDE\":null,\"AISLESECTION\":\"00\",\"SHELF\":null,\"HASSALES\":null},{\"UPC\":\"21190400000\",\"UNITOFMEASURE\":\"KG\",\"AISLE\":\"70\",\"AISLETYPE\":\"A\",\"SIDE\":null,\"AISLESECTION\":\"00\",\"SHELF\":null,\"HASSALES\":\"X\"}],\"PRIMARYVENDOR\":\"0000213623\",\"LOTSIZE\":null,\"ROUNDINGVALUE\":0.000,\"SITE_STATUS\":null}],\"SapWarehouses\":[],\"SapSales\":[{\"SALES_ORGANIZATION\":\"3000\",\"DISTRIBUTION_CHANNEL\":\"48\",\"DISTRIBUTION_CHAIN_ART_STATUS\":\"NO\",\"DISTR_CHAIN_SPEC_VALID_FROM\":\"2012-07-06\",\"UNIT_OF_MEASURE_OF_DELIVERY\":\"KG\",\"SALES_UNIT\":\"KG\",\"ARTICLE_PRICING_GROUP\":null,\"ACCOUNT_ASSIGNMENT_GROUP\":null,\"DISTRIBUTION_CHANNEL_NAME\":null,\"COMBINED_CONSUM_OR_REF_ARTICLE\":null,\"STORE_INVETORY_MASTER_ITEM\":null,\"AVERAGE_UNIT_WEIGHT\":0.67,\"WEB_ONLINE_FLAG\":\"Y\",\"TARE_CODE\":null,\"WEB_AVAILABLE_FROM\":\"2020-11-18T00:00:00.000Z\",\"WEB_AVAILABLE_TO\":\"9999-12-31T23:59:59.000Z\",\"MUST_CARRY_FLAG\":null,\"ONLINE_PORTION_ID\":0,\"ONLINE_PORTION_QUANTITY\":\"000\",\"ONLINE_PORTION_DESCRIPTION\":null,\"PROMOTIONAL_FAMILY_GROUPING\":null,\"SOBEYS_NATIONAL_PHARMACY_GROUP\":null,\"MAXIMUM_WEIGHT\":\"       0.925\",\"MINIMUM_WEIGHT\":\"       0.420\",\"NATIONALPHARMACYGROUP\":null,\"LISTEDFROM\":\"2012-04-26\",\"LISTEDTO\":\"9999-12-31\",\"CATCHWEIGHTUNIT\":\"KG\",\"SapBannernames\":[{\"LANGUAGE\":\"E\",\"NAME\":\"Sobeys MARM\"},{\"LANGUAGE\":\"F\",\"NAME\":\"Sobeys MARM\"}]},{\"SALES_ORGANIZATION\":\"3000\",\"DISTRIBUTION_CHANNEL\":\"49\",\"DISTRIBUTION_CHAIN_ART_STATUS\":\"NO\",\"DISTR_CHAIN_SPEC_VALID_FROM\":\"2012-07-06\",\"UNIT_OF_MEASURE_OF_DELIVERY\":\"KG\",\"SALES_UNIT\":\"KG\",\"ARTICLE_PRICING_GROUP\":null,\"ACCOUNT_ASSIGNMENT_GROUP\":null,\"DISTRIBUTION_CHANNEL_NAME\":null,\"COMBINED_CONSUM_OR_REF_ARTICLE\":null,\"STORE_INVETORY_MASTER_ITEM\":null,\"AVERAGE_UNIT_WEIGHT\":0.66,\"WEB_ONLINE_FLAG\":\"Y\",\"TARE_CODE\":null,\"WEB_AVAILABLE_FROM\":\"2021-03-12T00:00:00.000Z\",\"WEB_AVAILABLE_TO\":\"9999-12-31T23:59:59.000Z\",\"MUST_CARRY_FLAG\":null,\"ONLINE_PORTION_ID\":0,\"ONLINE_PORTION_QUANTITY\":\"000\",\"ONLINE_PORTION_DESCRIPTION\":null,\"PROMOTIONAL_FAMILY_GROUPING\":null,\"SOBEYS_NATIONAL_PHARMACY_GROUP\":null,\"MAXIMUM_WEIGHT\":\"       0.915\",\"MINIMUM_WEIGHT\":\"       0.420\",\"NATIONALPHARMACYGROUP\":null,\"LISTEDFROM\":\"2012-04-26\",\"LISTEDTO\":\"9999-12-31\",\"CATCHWEIGHTUNIT\":\"KG\",\"SapBannernames\":[{\"LANGUAGE\":\"E\",\"NAME\":\"Sobeys NFLD\"},{\"LANGUAGE\":\"F\",\"NAME\":\"Sobeys T-N\"}]},{\"SALES_ORGANIZATION\":\"3000\",\"DISTRIBUTION_CHANNEL\":\"56\",\"DISTRIBUTION_CHAIN_ART_STATUS\":null,\"DISTR_CHAIN_SPEC_VALID_FROM\":\"0000-00-00\",\"UNIT_OF_MEASURE_OF_DELIVERY\":\"KG\",\"SALES_UNIT\":\"CS\",\"ARTICLE_PRICING_GROUP\":null,\"ACCOUNT_ASSIGNMENT_GROUP\":null,\"DISTRIBUTION_CHANNEL_NAME\":null,\"COMBINED_CONSUM_OR_REF_ARTICLE\":null,\"STORE_INVETORY_MASTER_ITEM\":null,\"AVERAGE_UNIT_WEIGHT\":0.00,\"WEB_ONLINE_FLAG\":null,\"TARE_CODE\":null,\"WEB_AVAILABLE_FROM\":\"0000-00-00T00:00:00.000Z\",\"WEB_AVAILABLE_TO\":\"0000-00-00T23:59:59.000Z\",\"MUST_CARRY_FLAG\":null,\"ONLINE_PORTION_ID\":0,\"ONLINE_PORTION_QUANTITY\":\"000\",\"ONLINE_PORTION_DESCRIPTION\":null,\"PROMOTIONAL_FAMILY_GROUPING\":null,\"SOBEYS_NATIONAL_PHARMACY_GROUP\":null,\"MAXIMUM_WEIGHT\":null,\"MINIMUM_WEIGHT\":null,\"NATIONALPHARMACYGROUP\":null,\"LISTEDFROM\":\"2012-04-26\",\"LISTEDTO\":\"9999-12-31\",\"CATCHWEIGHTUNIT\":null,\"SapBannernames\":[{\"LANGUAGE\":\"E\",\"NAME\":\"DC Revenue Recogniti\"},{\"LANGUAGE\":\"F\",\"NAME\":\"Ventes entrepots\"}]},{\"SALES_ORGANIZATION\":\"3000\",\"DISTRIBUTION_CHANNEL\":\"60\",\"DISTRIBUTION_CHAIN_ART_STATUS\":null,\"DISTR_CHAIN_SPEC_VALID_FROM\":\"0000-00-00\",\"UNIT_OF_MEASURE_OF_DELIVERY\":\"KG\",\"SALES_UNIT\":\"CS\",\"ARTICLE_PRICING_GROUP\":null,\"ACCOUNT_ASSIGNMENT_GROUP\":null,\"DISTRIBUTION_CHANNEL_NAME\":null,\"COMBINED_CONSUM_OR_REF_ARTICLE\":null,\"STORE_INVETORY_MASTER_ITEM\":null,\"AVERAGE_UNIT_WEIGHT\":0.00,\"WEB_ONLINE_FLAG\":null,\"TARE_CODE\":null,\"WEB_AVAILABLE_FROM\":\"0000-00-00T00:00:00.000Z\",\"WEB_AVAILABLE_TO\":\"0000-00-00T23:59:59.000Z\",\"MUST_CARRY_FLAG\":null,\"ONLINE_PORTION_ID\":0,\"ONLINE_PORTION_QUANTITY\":\"000\",\"ONLINE_PORTION_DESCRIPTION\":null,\"PROMOTIONAL_FAMILY_GROUPING\":null,\"SOBEYS_NATIONAL_PHARMACY_GROUP\":null,\"MAXIMUM_WEIGHT\":null,\"MINIMUM_WEIGHT\":null,\"NATIONALPHARMACYGROUP\":null,\"LISTEDFROM\":\"2012-04-26\",\"LISTEDTO\":\"9999-12-31\",\"CATCHWEIGHTUNIT\":null,\"SapBannernames\":[{\"LANGUAGE\":\"E\",\"NAME\":\"DC's Corporate\"},{\"LANGUAGE\":\"F\",\"NAME\":\"CD Socit\"}]}],\"SapBillofmaterials\":[],\"SapArticledepartmentgrouping\":[{\"SALES_ORGANIZATION\":\"3000\",\"SITE_GROUP\":\"01\",\"PROFIT_CENTER\":\"001\",\"POS_DEPARTMENT\":\"001\"},{\"SALES_ORGANIZATION\":\"3000\",\"SITE_GROUP\":\"02\",\"PROFIT_CENTER\":\"050\",\"POS_DEPARTMENT\":\"050\"},{\"SALES_ORGANIZATION\":\"3000\",\"SITE_GROUP\":\"05\",\"PROFIT_CENTER\":\"072\",\"POS_DEPARTMENT\":\"001\"},{\"SALES_ORGANIZATION\":\"3000\",\"SITE_GROUP\":\"07\",\"PROFIT_CENTER\":\"089\",\"POS_DEPARTMENT\":\"004\"},{\"SALES_ORGANIZATION\":\"3000\",\"SITE_GROUP\":\"08\",\"PROFIT_CENTER\":\"095\",\"POS_DEPARTMENT\":\"095\"},{\"SALES_ORGANIZATION\":\"3000\",\"SITE_GROUP\":\"09\",\"PROFIT_CENTER\":\"098\",\"POS_DEPARTMENT\":\"098\"},{\"SALES_ORGANIZATION\":\"3000\",\"SITE_GROUP\":\"13\",\"PROFIT_CENTER\":\"141\",\"POS_DEPARTMENT\":\"001\"}],\"SapNationalrecyclecodes\":{\"REGION\":\"AMS\",\"SapRecycle1\":{\"CODE\":null,\"WEIGHT\":0.000},\"SapRecycle2\":{\"CODE\":null,\"WEIGHT\":0.000},\"SapRecycle3\":{\"CODE\":null,\"WEIGHT\":0.000},\"SapRecycle4\":{\"CODE\":null,\"WEIGHT\":0.000},\"SapRecycle5\":{\"CODE\":null,\"WEIGHT\":0.000},\"SapRecycle6\":{\"CODE\":null,\"WEIGHT\":0.000},\"SapRecycle7\":{\"CODE\":null,\"WEIGHT\":0.000},\"SapRecycle8\":{\"CODE\":null,\"WEIGHT\":0.000},\"SapRecycle9\":{\"CODE\":null,\"WEIGHT\":0.000},\"SapRecycle10\":{\"CODE\":null,\"WEIGHT\":0.000}},\"SapQuebecrecyclecodes\":{\"REGION\":\"AMS\",\"SapRecycle1\":[],\"SapRecycle2\":[],\"SapRecycle3\":[],\"SapRecycle4\":[]},\"SapBottledeposits\":[],\"SapCategorymanager\":[{\"SALES_ORGANIZATION\":\"3000\",\"CATEGORY_MANAGER_ID\":\"7504\",\"CATEGORY_MANAGER_NAME\":\"BEEF\"}],\"SapProvincialtaxes\":[{\"SALES_ORGANIZATION\":\"3000\",\"REGION_PROVINCE\":\"ON\",\"UNIT_OF_MEASURE_FOR_DISPLAY\":null,\"PREPARED_FOOD_TAX_CONDITIONAL\":null,\"PREPARED_FOOD_TAX_QUALIFYING\":null,\"SWEET_BAKED_GOODS\":null,\"GST_FLAG\":null,\"PST_FLAG\":\"Y\"}],\"SapLiquorcodes\":[],\"SapNutrition\":{\"REGION\":\"AMS\",\"SapDescriptions\":[{\"LANGUAGE\":\"E\",\"DESCRIPTION\":null},{\"LANGUAGE\":\"F\",\"DESCRIPTION\":null}],\"SERVINGSIZE\":0.000,\"SERVINGUNITOFMEASURE\":null,\"CALORIES\":\"000000\",\"TOTALFAT\":0.0,\"TOTALFATPERCENT\":\"000000\",\"SATURATEDFAT\":0.0,\"TRANSFAT\":0.0,\"SATURATEDTRANSFATPERCENT\":\"000000\",\"OMEGA6\":0.0,\"OMEGA3\":0.0,\"MONOUNSATURATEDFAT\":0.0,\"SUGARALCOHOLS\":\"000000\",\"CHOLESTEROL\":\"000000\",\"CHOLESTEROLPERCENT\":\"000000\",\"SODIUM\":\"000000\",\"SODIUMPERCENT\":\"000000\",\"POTASSIUM\":\"000000\",\"POTASSIUMPERCENT\":\"000000\",\"TOTALCARBOHYDRATE\":\"000000\",\"TOTALCARBOHYDRATEPERCENT\":\"000000\",\"FIBRE\":\"000000\",\"FIBREPERCENT\":\"000000\",\"SUGAR\":\"000000\",\"PROTEIN\":0.0,\"VITAMINAPERCENT\":\"000000\",\"VITAMINCPERCENT\":\"000000\",\"CALCIUMPERCENT\":\"000000\",\"IRONPERCENT\":\"000000\",\"NONSWEETCLAIMS\":null,\"PRODUCTDEVELOPER\":null,\"PRODUCTOWNER\":null,\"NUTRITIONFLAG\":null,\"SapRegionalnutritiondata\":[]},\"SapArticleSubstitution\":[{\"SALES_ORGANIZATION\":\"3000\",\"DETERMINATION_TYPE\":\"Z002\",\"DISTRIBUTION_CHANNEL\":\"48\",\"CUSTOMER_GROUP\":null,\"SITE_NUMBER\":\"0370\",\"VALID_FROM\":\"2020-11-28\",\"VALID_TO\":\"9999-12-31\",\"SUBSTITUTE_ARTICLE\":\"000000000000044197\",\"REASON_OF_SUBSTITUTION\":\"ZVO\",\"UNITOFMEASURE\":\"KG\",\"SUBSTITUTIONQUANTITY\":\"00001\",\"REASON_DESCRIPTION_EN\":\"vndr short  -orig\\/\",\"REASON_DESCRIPTION_FR\":\"Rupt. fourn. -orig.\\/\"},{\"SALES_ORGANIZATION\":\"3000\",\"DETERMINATION_TYPE\":\"Z002\",\"DISTRIBUTION_CHANNEL\":\"48\",\"CUSTOMER_GROUP\":null,\"SITE_NUMBER\":\"0495\",\"VALID_FROM\":\"2021-04-02\",\"VALID_TO\":\"9999-12-31\",\"SUBSTITUTE_ARTICLE\":\"000000000000044197\",\"REASON_OF_SUBSTITUTION\":\"ZVO\",\"UNITOFMEASURE\":\"KG\",\"SUBSTITUTIONQUANTITY\":\"00001\",\"REASON_DESCRIPTION_EN\":\"vndr short  -orig\\/\",\"REASON_DESCRIPTION_FR\":\"Rupt. fourn. -orig.\\/\"},{\"SALES_ORGANIZATION\":\"3000\",\"DETERMINATION_TYPE\":\"Z002\",\"DISTRIBUTION_CHANNEL\":\"48\",\"CUSTOMER_GROUP\":null,\"SITE_NUMBER\":\"0628\",\"VALID_FROM\":\"2021-03-16\",\"VALID_TO\":\"9999-12-31\",\"SUBSTITUTE_ARTICLE\":\"000000000000044197\",\"REASON_OF_SUBSTITUTION\":\"ZVO\",\"UNITOFMEASURE\":\"KG\",\"SUBSTITUTIONQUANTITY\":\"00001\",\"REASON_DESCRIPTION_EN\":\"vndr short  -orig\\/\",\"REASON_DESCRIPTION_FR\":\"Rupt. fourn. -orig.\\/\"},{\"SALES_ORGANIZATION\":\"3000\",\"DETERMINATION_TYPE\":\"Z002\",\"DISTRIBUTION_CHANNEL\":\"48\",\"CUSTOMER_GROUP\":null,\"SITE_NUMBER\":\"0630\",\"VALID_FROM\":\"2021-02-03\",\"VALID_TO\":\"9999-12-31\",\"SUBSTITUTE_ARTICLE\":\"000000000000044197\",\"REASON_OF_SUBSTITUTION\":\"ZVO\",\"UNITOFMEASURE\":\"KG\",\"SUBSTITUTIONQUANTITY\":\"00001\",\"REASON_DESCRIPTION_EN\":\"vndr short  -orig\\/\",\"REASON_DESCRIPTION_FR\":\"Rupt. fourn. -orig.\\/\"},{\"SALES_ORGANIZATION\":\"3000\",\"DETERMINATION_TYPE\":\"Z002\",\"DISTRIBUTION_CHANNEL\":\"49\",\"CUSTOMER_GROUP\":null,\"SITE_NUMBER\":\"0744\",\"VALID_FROM\":\"2021-03-16\",\"VALID_TO\":\"9999-12-31\",\"SUBSTITUTE_ARTICLE\":\"000000000000044197\",\"REASON_OF_SUBSTITUTION\":\"ZVO\",\"UNITOFMEASURE\":\"KG\",\"SUBSTITUTIONQUANTITY\":\"00001\",\"REASON_DESCRIPTION_EN\":\"vndr short  -orig\\/\",\"REASON_DESCRIPTION_FR\":\"Rupt. fourn. -orig.\\/\"}],\"SapArticlehierarchynodes\":[{\"NODE\":\"SBY\",\"TREE_LEVEL\":\"01\",\"SapDescriptions\":[{\"LANGUAGE\":\"E\",\"DESCRIPTION\":\"SOBEYS CDT ATLANTIC\"}]},{\"NODE\":\"M40\",\"TREE_LEVEL\":\"02\",\"SapDescriptions\":[{\"LANGUAGE\":\"E\",\"DESCRIPTION\":\"Meat\"},{\"LANGUAGE\":\"F\",\"DESCRIPTION\":\"VIANDE\"}]},{\"NODE\":\"M4015\",\"TREE_LEVEL\":\"03\",\"SapDescriptions\":[{\"LANGUAGE\":\"E\",\"DESCRIPTION\":\"Fresh Beef\"},{\"LANGUAGE\":\"F\",\"DESCRIPTION\":\"BOEUF\"}]},{\"NODE\":\"40-15-03\",\"TREE_LEVEL\":\"04\",\"SapDescriptions\":[{\"LANGUAGE\":\"E\",\"DESCRIPTION\":\"Frsh Bf Shldr\"},{\"LANGUAGE\":\"F\",\"DESCRIPTION\":\"BOEUF EPAULE\"}]},{\"NODE\":\"400-15-10\",\"TREE_LEVEL\":\"05\",\"SapDescriptions\":[{\"LANGUAGE\":\"E\",\"DESCRIPTION\":\"Frsh Bf Shldr CrRib\"},{\"LANGUAGE\":\"F\",\"DESCRIPTION\":\"BOEUF COTES CROISEES\"}]},{\"NODE\":\"400-15-10-07\",\"TREE_LEVEL\":\"06\",\"SapDescriptions\":[{\"LANGUAGE\":\"E\",\"DESCRIPTION\":\"Frsh Bf Shldr CrRib StrlSlvr\"},{\"LANGUAGE\":\"F\",\"DESCRIPTION\":\"BOEUF COTES CROISEES SS\"}]},{\"NODE\":\"400-15-10-07-01\",\"TREE_LEVEL\":\"07\",\"SapDescriptions\":[{\"LANGUAGE\":\"E\",\"DESCRIPTION\":\"Frsh Bf Shldr CrRib StrlSlvr\"},{\"LANGUAGE\":\"F\",\"DESCRIPTION\":\"BOEUF COTES CROISEES SS\"}]},{\"NODE\":\"400-15-10-07-011\",\"TREE_LEVEL\":\"08\",\"SapDescriptions\":[{\"LANGUAGE\":\"E\",\"DESCRIPTION\":\"Frsh Bf Shldr CrRib StrlSlvr\"},{\"LANGUAGE\":\"F\",\"DESCRIPTION\":\"BOEUF COTES CROISEES SS\"}]}],\"SapItrade\":{\"REGION\":\"AMS\",\"HSCODE\":null,\"CATEGORY\":null,\"CATEGORYDESCRIPTION\":null,\"LABEL\":null,\"GRADE\":null,\"SIZE\":null,\"PACKAGE\":null,\"CONTAINER\":null,\"GROWTYPE\":null,\"GROWPROCESS\":null,\"PRODUCTORIGIN\":null},\"SapSitegroups\":[],\"SapTaxclassification\":[{\"SALES_ORGANIZATION\":\"3000\",\"REGION\":\"AB\",\"UNIT_OF_MEASURE\":null,\"TAXCODE1\":\"N\",\"TAXCODE2\":\"N\",\"TAXCODE3\":\"N\",\"TAXCODE4\":\"N\",\"TAX_CONDITIONAL\":\"N\",\"TAX_QUALIFYING\":\"N\",\"SWEET_BAKED_GOODS\":\"N\",\"OSP_TAXTYPE\":\"Z\",\"OSP_ADDITIONALFLAG\":null,\"VALID_FROM\":\"2020-01-01\",\"VALID_TO\":\"0000-00-00\"},{\"SALES_ORGANIZATION\":\"3000\",\"REGION\":\"BC\",\"UNIT_OF_MEASURE\":null,\"TAXCODE1\":\"N\",\"TAXCODE2\":\"N\",\"TAXCODE3\":\"N\",\"TAXCODE4\":\"N\",\"TAX_CONDITIONAL\":\"N\",\"TAX_QUALIFYING\":\"N\",\"SWEET_BAKED_GOODS\":\"N\",\"OSP_TAXTYPE\":\"Z\",\"OSP_ADDITIONALFLAG\":null,\"VALID_FROM\":\"2020-01-01\",\"VALID_TO\":\"0000-00-00\"},{\"SALES_ORGANIZATION\":\"3000\",\"REGION\":\"MB\",\"UNIT_OF_MEASURE\":null,\"TAXCODE1\":\"N\",\"TAXCODE2\":\"N\",\"TAXCODE3\":\"N\",\"TAXCODE4\":\"N\",\"TAX_CONDITIONAL\":\"N\",\"TAX_QUALIFYING\":\"N\",\"SWEET_BAKED_GOODS\":\"N\",\"OSP_TAXTYPE\":\"Z\",\"OSP_ADDITIONALFLAG\":null,\"VALID_FROM\":\"2020-01-01\",\"VALID_TO\":\"0000-00-00\"},{\"SALES_ORGANIZATION\":\"3000\",\"REGION\":\"NB\",\"UNIT_OF_MEASURE\":null,\"TAXCODE1\":\"N\",\"TAXCODE2\":\"N\",\"TAXCODE3\":\"N\",\"TAXCODE4\":\"N\",\"TAX_CONDITIONAL\":\"N\",\"TAX_QUALIFYING\":\"N\",\"SWEET_BAKED_GOODS\":\"N\",\"OSP_TAXTYPE\":\"Z\",\"OSP_ADDITIONALFLAG\":null,\"VALID_FROM\":\"2020-01-01\",\"VALID_TO\":\"0000-00-00\"},{\"SALES_ORGANIZATION\":\"3000\",\"REGION\":\"NL\",\"UNIT_OF_MEASURE\":null,\"TAXCODE1\":\"N\",\"TAXCODE2\":\"N\",\"TAXCODE3\":\"N\",\"TAXCODE4\":\"N\",\"TAX_CONDITIONAL\":\"N\",\"TAX_QUALIFYING\":\"N\",\"SWEET_BAKED_GOODS\":\"N\",\"OSP_TAXTYPE\":\"Z\",\"OSP_ADDITIONALFLAG\":null,\"VALID_FROM\":\"2020-01-01\",\"VALID_TO\":\"0000-00-00\"},{\"SALES_ORGANIZATION\":\"3000\",\"REGION\":\"NS\",\"UNIT_OF_MEASURE\":null,\"TAXCODE1\":\"N\",\"TAXCODE2\":\"N\",\"TAXCODE3\":\"N\",\"TAXCODE4\":\"N\",\"TAX_CONDITIONAL\":\"N\",\"TAX_QUALIFYING\":\"N\",\"SWEET_BAKED_GOODS\":\"N\",\"OSP_TAXTYPE\":\"Z\",\"OSP_ADDITIONALFLAG\":null,\"VALID_FROM\":\"2020-01-01\",\"VALID_TO\":\"0000-00-00\"},{\"SALES_ORGANIZATION\":\"3000\",\"REGION\":\"NT\",\"UNIT_OF_MEASURE\":null,\"TAXCODE1\":\"N\",\"TAXCODE2\":\"N\",\"TAXCODE3\":\"N\",\"TAXCODE4\":\"N\",\"TAX_CONDITIONAL\":\"N\",\"TAX_QUALIFYING\":\"N\",\"SWEET_BAKED_GOODS\":\"N\",\"OSP_TAXTYPE\":\"Z\",\"OSP_ADDITIONALFLAG\":null,\"VALID_FROM\":\"2020-01-01\",\"VALID_TO\":\"0000-00-00\"},{\"SALES_ORGANIZATION\":\"3000\",\"REGION\":\"NU\",\"UNIT_OF_MEASURE\":null,\"TAXCODE1\":\"N\",\"TAXCODE2\":\"N\",\"TAXCODE3\":\"N\",\"TAXCODE4\":\"N\",\"TAX_CONDITIONAL\":\"N\",\"TAX_QUALIFYING\":\"N\",\"SWEET_BAKED_GOODS\":\"N\",\"OSP_TAXTYPE\":\"Z\",\"OSP_ADDITIONALFLAG\":null,\"VALID_FROM\":\"2020-01-01\",\"VALID_TO\":\"0000-00-00\"},{\"SALES_ORGANIZATION\":\"3000\",\"REGION\":\"ON\",\"UNIT_OF_MEASURE\":null,\"TAXCODE1\":\"N\",\"TAXCODE2\":\"N\",\"TAXCODE3\":\"N\",\"TAXCODE4\":\"N\",\"TAX_CONDITIONAL\":\"N\",\"TAX_QUALIFYING\":\"N\",\"SWEET_BAKED_GOODS\":\"N\",\"OSP_TAXTYPE\":\"Z\",\"OSP_ADDITIONALFLAG\":null,\"VALID_FROM\":\"2020-01-01\",\"VALID_TO\":\"0000-00-00\"},{\"SALES_ORGANIZATION\":\"3000\",\"REGION\":\"PE\",\"UNIT_OF_MEASURE\":null,\"TAXCODE1\":\"N\",\"TAXCODE2\":\"N\",\"TAXCODE3\":\"N\",\"TAXCODE4\":\"N\",\"TAX_CONDITIONAL\":\"N\",\"TAX_QUALIFYING\":\"N\",\"SWEET_BAKED_GOODS\":\"N\",\"OSP_TAXTYPE\":\"Z\",\"OSP_ADDITIONALFLAG\":null,\"VALID_FROM\":\"2020-01-01\",\"VALID_TO\":\"0000-00-00\"},{\"SALES_ORGANIZATION\":\"3000\",\"REGION\":\"QC\",\"UNIT_OF_MEASURE\":null,\"TAXCODE1\":\"N\",\"TAXCODE2\":\"N\",\"TAXCODE3\":\"N\",\"TAXCODE4\":\"N\",\"TAX_CONDITIONAL\":\"N\",\"TAX_QUALIFYING\":\"N\",\"SWEET_BAKED_GOODS\":\"N\",\"OSP_TAXTYPE\":\"Z\",\"OSP_ADDITIONALFLAG\":null,\"VALID_FROM\":\"2020-01-01\",\"VALID_TO\":\"0000-00-00\"},{\"SALES_ORGANIZATION\":\"3000\",\"REGION\":\"SK\",\"UNIT_OF_MEASURE\":null,\"TAXCODE1\":\"N\",\"TAXCODE2\":\"N\",\"TAXCODE3\":\"N\",\"TAXCODE4\":\"N\",\"TAX_CONDITIONAL\":\"N\",\"TAX_QUALIFYING\":\"N\",\"SWEET_BAKED_GOODS\":\"N\",\"OSP_TAXTYPE\":\"Z\",\"OSP_ADDITIONALFLAG\":null,\"VALID_FROM\":\"2020-01-01\",\"VALID_TO\":\"0000-00-00\"},{\"SALES_ORGANIZATION\":\"3000\",\"REGION\":\"YT\",\"UNIT_OF_MEASURE\":null,\"TAXCODE1\":\"N\",\"TAXCODE2\":\"N\",\"TAXCODE3\":\"N\",\"TAXCODE4\":\"N\",\"TAX_CONDITIONAL\":\"N\",\"TAX_QUALIFYING\":\"N\",\"SWEET_BAKED_GOODS\":\"N\",\"OSP_TAXTYPE\":\"Z\",\"OSP_ADDITIONALFLAG\":null,\"VALID_FROM\":\"2020-01-01\",\"VALID_TO\":\"0000-00-00\"}],\"SapSalesset\":[],\"SapCustomerAssortment\":[],\"SapPriceFamilies\":[],\"MANUALLYSENT\":\"X\",\"SAP_DISPATCH_TS\":\"20210818114606\"}]}\r\n}",
							"options": {
								"raw": {
									"language": "json"
								}
							}
						},
						"url": {
							"raw": "https://nonprod.apis.sobeys.com/dev/sobeys-sapevents-p-api/v1/uploadData",
							"protocol": "https",
							"host": [
								"nonprod",
								"apis",
								"sobeys",
								"com"
							],
							"path": [
								"dev",
								"sobeys-sapevents-p-api",
								"v1",
								"uploadData"
							]
						}
					},
					"response": []
				}
			]
		}
	]
}